{
	"名称": "云铝股份",
	"code": "000807",
	"全名": "云南铝业股份有限公司",
	"地域": "云南省",
	"分类": "大盘股",
	"财务": "",
	"行业": "有色金属—工业金属",
	"业务": "铝土矿开采、氧化铝生产、铝冶炼、铝加工及铝用阳极炭素生产和销售。",
	"产品": "氧化铝、铝用阳极炭素、重熔用铝锭、圆铝杆、铝合金、铝板带箔、铝焊材",
	"概念": "俄乌冲突概念，央企国资改革，一季报预增，MSCI概念，标普道琼斯A股，工业互联网，燃料电池，融资融券，深股通，碳交易，新能源汽车",
	"概念y": "中证500-100%  深证成指-100%  铝空气电池-59%  融资融券-33%  电解铝-24%  业绩预增-23%  铝-22%  工业互联网-19%  有色金属-13%  新能源汽车-10%  石墨电极-10%  股权转让-10%  电改-10%  工业4.0-10%  炭素-9%  稀有金属-8%  深股通-8%  深港通-6%  稀缺资源-5%  涉矿-3%  氢燃料电池-3%  贵金属-2%",
	"概念详情": {
		"央企国资改革": "公司实控人为国务院国有资产监督管理委员会，属于国资委。",
		"燃料电池": "与以色列斐源新能源科技有限公司和上海佐永新能源科技有限公司共同在昆明市设立云南创能斐源金属燃料电池有限公司,从事铝空气能源系统及其配套产品;云铝股份、佐永科技公司、斐源公司对合资公司的出资比例分别为32%、36%、32%",
		"新能源汽车": "公司拟与拥有世界领先水平铝-空气电池技术和新能源汽车动力电池产业化技术的以色列斐源新能源科技有限公司和与斐源公司在中国区保持良好合作关系、拥有灵活高效民营机制的上海佐永新能源科技有限公司共同在昆明市设立云南创能斐源金属燃料电池有限公司。2017年12月13日晚公告，拟收购创能公司余下的66%股权。收购完成后创能公司将成为云铝股份的全资子公司。该公司为铝空气电池研发的平台公司，云铝股份还称创能公司与另一公司的部分产品已进入应用测试阶段。云铝股份公告称，创能公司和慧创绿能在通信基站备用电源、应急备用电源及新能源车配套电源等领域的产品研发和产业化运用取得了积极进展，部分产品已进入应用测试阶段，测试效果达到预期标准。",
		"股权转让": "18年11月，云南省国资委拟将控股股东云冶集团51%股权划转至中铝集团全资子公司中国铜业，公司实控人变为国务院国资委.",
		"工业互联网": "电解铝智能制造技术开发应用及智慧工厂建设项目”入选2018年工业互联网试点示范项目名单",
		"标普道琼斯A股": "2018年12月1日，指数编制公司标普道琼斯宣布，将部分中国A股纳入其全球指数体系，分类基本为新兴市场。2019年9月，标普道琼斯新兴市场指数以25%的纳入因子纳入A股。"
	},
	"亮点": "主营电解铝、铝加工制品的大型铝业集团",
	"同业": "铝:  天山铝业  中国铝业  南山铝业  神火股份  焦作万方  *ST中孚"
}