{
	"名称": "美能能源",
	"code": "001299",
	"亮点": "城市燃气综合运营服务商",
	"概念": "天然气，西部大开发，物联网",
	"同业": "油气销售:  和顺石油  洪通燃气  胜通能源  恒通股份  国际实业  泰山石油  广聚能源",
	"分类": "小盘股",
	"全名": "陕西美能清洁能源集团股份有限公司",
	"地域": "陕西省",
	"行业": "公用事业—燃气Ⅱ",
	"业务": "城镇燃气的输配与运营业务，包括天然气终端销售和服务以及天然气用户设施设备安装业务。",
	"产品": "天然气销售、天然气设施设备安装、其他业务",
	"概念详情": {
		"天然气": "公司的主营业务是城镇燃气的输配与运营业务，包括天然气终端销售和服务以及天然气用户设施设备安装业务。公司的主要产品是天然气销售、天然气设施设备安装、其他业务。",
		"西部大开发": "公司注册地址为陕西省西安市雁塔区高新区科技路48号创业广场B1605室",
		"物联网": "2022年10月17日互动易：为提高公司信息化管理水平和方便广大用户，公司自2018年5月开始对所有新装非居民用户采用物联网表进行安装与计量，自2019年3月开始对所有新装居民用户采用物联网表进行安装与计量。截至当前，公司非居民用户已安装物联网表2,000余户，居民用户已安装物联网表7.3万多户。对于以前已经安装的20多万IC卡表用户，公司将根据其使用年限按计划逐年更换成物联网表，未来用户可通过微信公众号、企业APP等多种方式进行缴费充值。"
	},
	"概念x": "天然气",
	"概念xgb": {
		"天然气": "专业化城市燃气综合运营服务商，省燃气热力协会副理事长单位；公司主营业务以城镇燃气输配与运营为核心，含天然气终端销售和设施安装（服务 37 万居民、4900 工商业用户），建成 1684 公里管网、8 座门站及 4 座 CNG 加气站，气源来自中石油，经营陕西 “两市一区”"
	}
}