{
	"名称": "多利科技",
	"code": "001311",
	"亮点": "主营汽车冲压零部件及相关模具，前纵梁、水箱板总成国内乘用车市场占有率3%以上",
	"概念": "一体化压铸，特斯拉，新能源汽车，核准制次新股，理想汽车概念，深股通，蔚来汽车概念，新股与次新股",
	"同业": "汽车压铸件:  旭升集团  爱柯迪  广东鸿图  文灿股份  春兴精工  联诚精密  嵘泰股份  明志科技  浙江黎明  铭科精技  联合精密  晋拓股份  星源卓镁  亚通精工  祥鑫科技",
	"分类": "小盘股",
	"全名": "滁州多利汽车科技股份有限公司",
	"地域": "安徽省",
	"行业": "汽车—汽车零部件",
	"业务": "汽车冲压零部件及相关模具的开发、生产与销售。",
	"产品": "前纵梁、水箱板总成、后纵梁、天窗框、轮罩、门窗框、顶盖梁、A柱内板、B柱加强板、挡泥板、单冲模、多工位模、级进模",
	"概念详情": {
		"一体化压铸": "2023年3月3日互动易回复：公司全资子公司昆山达亚汽车零部件有限公司汽车电池托盘、冲压件生产项目为公司IPO募投项目之一，公司将适应市场发展，开拓配套客户。公司较早跟进一体化压铸技术，并进行了人才及技术储备，并积极布局厂房及生产设备。",
		"特斯拉": "公司2022年1-6月对主要客户特斯拉的销售收入为6.15亿元，较去年同期增长61.37%，公司对主要客户理想汽车的销售收入为1.70亿元，较去年同期增长91.99%。",
		"新能源汽车": "2023年2月6日招股书显示公司在现有燃油整车制造商稳定配套合作的基础上,积极拓展布局新能源整车客户,并进入了特斯拉、理想汽车、蔚来汽车、零跑汽车和华人运通等知名新能源整车制造商的合格供应商。",
		"核准制次新股": "公司上市日期为2023-02-27，主营为汽车冲压零部件及相关模具的开发、生产与销售。",
		"新股与次新股": "公司上市日期为2023-02-27，主营为汽车冲压零部件及相关模具的开发、生产与销售。"
	}
}