{
	"名称": "楚环科技",
	"code": "001336",
	"亮点": "废气恶臭治理系统解决方案服务商",
	"概念": "专精特新，核准制次新股，节能环保，共同富裕示范区，碳中和，新股与次新股",
	"同业": "废物处理:  复洁环保  山高环能  圣元环保  建工修复  百川畅银  超越科技  军信股份  中科环保  丛麟科技  新动力  赛恩斯  国泰环保  卓越新能  三峰环境  启迪环境  绿色动力  伟明环保  东江环保  上海环境  富春环保  中国天楹  瀚蓝环境  高能环境  旺能环境  维尔利  朗坤环境  ST金圆",
	"分类": "小盘股",
	"全名": "杭州楚环科技股份有限公司",
	"地域": "浙江省",
	"行业": "环保—环保设备Ⅱ",
	"业务": "集研发、设计、制造、销售、服务为一体的废气恶臭治理系统解决方案服务商。",
	"产品": "生物除臭设备、离子除臭设备、水处理设备和设备维修服务",
	"概念详情": {
		"专精特新": "专精特新“小巨人”企业是全国中小企业评定工作中最高等级、最具权威的荣誉称号，是指专注于细分市场、创新能力强、市场占有率高、掌握关键核心技术、质量效益优的排头兵企业，对于提升中小企业自身的竞争力，以及提升产业链、供应链稳定性和竞争力具有重大意义。公司已入选工信部国家级专精特新小巨人企业名单。",
		"核准制次新股": "公司上市日期为2022-07-25，主营为集研发、设计、制造、销售、服务为一体的废气恶臭治理系统解决方案服务商。",
		"节能环保": "公司主要从事环保细分领域废气恶臭治理设备的研发、设计、生产和销售。",
		"新股与次新股": "公司上市日期为2022-07-25，主营为集研发、设计、制造、销售、服务为一体的废气恶臭治理系统解决方案服务商。",
		"共同富裕示范区": "公司地处浙江省杭州市拱墅区，是一家治理废气的民营环保企业。",
		"碳中和": "公司在互动易平台表示，公司的废弃处理设备专注于处理废气恶臭，减少了一定的碳排放。"
	}
}