{
	"名称": "正威新材",
	"code": "002201",
	"全名": "江苏正威新材料股份有限公司",
	"地域": "江苏省",
	"分类": "中盘股",
	"财务": "",
	"行业": "建筑材料—玻璃玻纤",
	"业务": "玻璃纤维深加工制品、玻璃纤维复合材料以及高性能玻璃纤维、高性能玻璃纤维增强基材的制造和销售。",
	"产品": "增强砂轮网片、增强砂轮网布、玻璃纤维自粘带、土工格栅及坯布、玻璃钢制品",
	"概念": "新材料概念，风电，轨道交通，三季报预增，芯片概念",
	"概念y": "玻璃纤维-100%  新材料-47%  玻璃-39%  壳公司-28%  特种玻璃-28%  江苏沿海地区-14%  壳资源-11%  甲醇-10%  纤维新材料-10%",
	"概念详情": {
		"风电": "2020年半年报披露：公司通过在风力发电复合材料叶片市场的多年布局，报告期内，已陆续获得江阴远景投资有限公司、山东中车风电有限公司、华锐风电科技（集团）股份有限公司、明阳智慧能源集团股份有限公司等风电主机厂家的订单，将于2020年下半年陆续实现销售。",
		"新材料概念": "公司主要从事玻璃纤维深加工制品，玻璃纤维复合材料及高性能玻璃纤维，高性能玻璃纤维增强基材的制造和销售。公司产品属于新材料领域，符合国家产业政策鼓励方向，是国家和行业政策中明确的重点发展领域。",
		"股权转让": "2019年7月份，公司实际控制人，控股股东顾清波先生正在筹划将其部分股份转让给深圳正威（集团）有限公司或其指定第三方，可能涉及公司控制权变更，交易对方所属行业是金属和非金属新材料领域。"
	},
	"亮点": "国内最大的纺织型玻纤制品生产商",
	"同业": "玻纤:  中国巨石  中材科技  长海股份  宏和科技  山东玻纤"
}