{
	"名称": "奥特佳",
	"code": "002239",
	"全名": "奥特佳新能源科技股份有限公司",
	"地域": "江苏省",
	"分类": "中盘股",
	"财务": "",
	"行业": "交运设备—汽车零部件",
	"业务": "汽车热管理系统技术开发、产品生产及销售",
	"产品": "汽车空调压缩机、汽车空调系统、服装",
	"概念": "北汽新能源，新能源汽车，特斯拉，人民币贬值受益，蔚来汽车概念",
	"概念y": "中证1000-100%  空调-53%  通州湾新区-49%  汽配-38%  新能源汽车-13%  新能源汽车-13%  深股通-12%  大上海-12%  特斯拉-12%  独角兽-10%  深港通-9%  江苏沿海地区-9%  锂电池-4%  北汽新能源-1%  涉矿-1%",
	"概念详情": {
		"北汽新能源": "2017年公司顺利通了比亚迪、北汽新能源、德国(大众)和一汽(大众)等国内外知名厂商的各项审核，成为其电动压缩机供应商。",
		"新能源汽车": "公司是国内汽车空调压缩机行业的领先企业，是中国汽车工业协会认定的“中国汽车零部件(空调)行业龙头企业”。2018年8月收购国电赛思,主要产品为双向电源设备,用于锂电池生产检测环节,可以降低电芯厂成本。",
		"特斯拉": "18年11月,子公司空调国际成为特斯拉供应商,将为特斯拉公司的某型号电动汽车供应汽车空调产品(HVAC)。",
		"人民币贬值受益": "目前主营业务中的产品约90%销往美国市场，是国内最大的美国中高档服装(女装)ODM与OBM厂商之一。"
	}
}