{
	"名称": "合兴包装",
	"code": "002228",
	"全名": "厦门合兴包装印刷股份有限公司",
	"地域": "福建省",
	"分类": "小盘股",
	"财务": "",
	"行业": "轻工制造—包装印刷",
	"业务": "中高档瓦楞纸箱、纸板及缓冲包装材料的研发与设计、生产、销售及服务。",
	"产品": "瓦楞纸箱、纸板、缓冲包装材料",
	"概念": "福建自贸区，数字水印，小米概念",
	"概念y": "人民币升值-100%  工业4.0-56%  食品包装-35%  环保包装-29%  工业用地-21%  联想产业链-17%  供应链金融-17%  造纸-12%  深股通-10%  机器人-10%  小米-10%  业绩预增-4%",
	"概念详情": {
		"福建自贸区": "公司办公地址处于福建省厦门市湖里区五缘湾同安商务大厦2号楼19楼",
		"数字水印": "2023年2月8日公司互动回复：公司将数字印刷与纸箱预印完美结合，实现“数字万花筒”、“数字水印”等应用。",
		"小米概念": "2018年3月19日互动易回复：公司目前主要是为小米手机提供外包装纸箱。"
	},
	"亮点": "专业化、规模化、一体化的综合包装企业",
	"同业": "纸包装:  环球印务  南王科技  上海艾录  大胜达  裕同科技  美盈森  光大同创  翔港科技  新通联  龙利得  森林包装  新巨丰  中荣股份  吉宏股份",
	"概念xgb": {
		"包装印刷": "瓦楞包装行业龙头；公司主要从事中高档瓦楞纸箱、纸板及缓冲包装材料的研发与设计、生产、销售及服务；公司的瓦楞纸箱以其优越的使用性能和良好的加工性能，逐渐取代了传统的木箱等运输包装容器，成为现代包装运输的主要载体；22年包装制造行业收入118.87亿元，营收占比77.31%",
		"小米概念股": "公司与小米保持着良好的合作关系，为小米提供纸箱包装等服务"
	},
	"概念x": "包装印刷   小米概念股"
}