{
	"名称": "新朋股份",
	"code": "002328",
	"全名": "上海新朋实业股份有限公司",
	"地域": "上海市",
	"分类": "小盘股",
	"财务": "",
	"行业": "汽车—汽车零部件",
	"业务": "汽车零部件类和金属及通信零部件类研发、生产和销售。",
	"产品": "金属及通信部件、汽车零部件、房产租赁",
	"概念": "创投，新能源汽车，长三角一体化，储能，集成电路概念，三季报预增，特斯拉，芯片概念",
	"概念y": "长三角一体化-100%  特斯拉-61%  蚂蚁金服-44%  创投-44%  涉矿-14%  航天军工-10%  独角兽-10%  储能-10%  证金持股-10%  汽车零部件-10%  进口博览会-10%  文化传媒-5%",
	"概念详情": {
		"新能源汽车": "公司获得部分新能源汽车项目的供应商资质，可以提供配套产品及服务。",
		"特斯拉": "2020年1月8日公司在互动平台称：公司有为TESLA供应家用储能项目配套产品。",
		"汽车电子": "2020年6月4日公告：新潮集团将利用自身资源优势，在公司现有业务拓展、制造技术升级和汽车电子领域的战略布局等各方面与新朋股份展开深入合作。",
		"创投": "2015年3月公司与汇付天下有限公司、上海朗程财务咨询有限公司及其他出资方拟共同出资设立上海汇付互联网金融信息服务创业股权投资中心，公司以现金方式,出资不超过人民币3,000万元。",
		"长三角一体化": "公司注册地址为上海市青浦区，主营业务为从事汽车零部件开卷、冲压、焊接，以及电视屏散热板、通讯机柜机箱等产品的生产和销售",
		"芯片概念": "公司年报披露：2019年12月，投资天津金海通自动化设备制造有限公司，投资金额4,286.72万元，占比为7.43%，其主要从事半导体封装测试设备开发与生产；投资上海伟测半导体科技有限公司，投资金额3,039.45万元，占比为5.76%，其主要从事集成电路芯片晶圆级测试及测试程序开发。",
		"集成电路概念": "2019年年报披露：2019年12月，投资上海伟测半导体科技有限公司，投资金额3,039.45万元，占比为5.76%，其主要从事集成电路芯片晶圆级测试及测试程序开发。"
	},
	"亮点": "国内专业的机电产品零部件制造商",
	"同业": "车身及附件:  松原股份  长华股份  明新旭腾  英利汽车  华达科技  常青股份  天汽模  华懋科技  凌云股份  贵航股份"
}