{
	"名称": "三维工程",
	"code": "002469",
	"全名": "山东三维石化工程股份有限公司",
	"地域": "山东省",
	"分类": "小盘股",
	"财务": "",
	"行业": "建筑装饰—专业工程",
	"业务": "工程设计及工程总承包;催化剂的生产及销售",
	"产品": "工程咨询、工程总承包、工程设计",
	"概念": "煤化工，固废处理，垃圾分类，节能环保，年报预增，氢能源，一带一路",
	"概念y": "煤制气-32%  一带一路-30%  油品升级-27%  基础设施建设-23%  煤化工-17%  汽油脱硫-12%  环保-11%  盐酸-10%  新疆节能环保-10%  证金持股-10%  节能环保-5%",
	"概念详情": {
		"煤化工": "公司利用在石化行业市场积累的丰富经验，通过技术攻关，成功将无在线炉硫磺回收工艺技术应用于煤化工领域。公司承接了全球首家煤直接液化项目神华煤制油项目3万吨/年硫磺回收装置设计；承做了总金额近亿元的神华包头煤化工公司2万吨/年硫磺回收装置的总承包项目，这是我国最早经国家核准的煤制烯烃项目；经过多年发展，公司逐步改变了我国煤化工行业硫磺回收依赖进口技术的局面。",
		"固废处理": "公司互动平台称青岛三维人和环保投资有限公司经营范围包含固体废物治理；土壤污染治理；大气污染治理；经营其他无须行政审批即可经营的一般经营项目”。",
		"垃圾分类": "2019年7月1日公司互动平台回复称2017年4月公司与北京锦龙恒业水务科技有限公司合资设立了青岛三维人和环保投资有限公司，公司认缴出资占比为40%。该公司营业执照经营范围为：“以自有资金对环保项目进行投资及运营（未经金融监管部门批准，不得从事吸收存款、融资担保、代客理财等金融业务）；污水处理；水污染治理；水处理设备的销售、安装、技术服务、技术咨询；从事环保领域内的技术开发、技术服务、技术转让、技术咨询；城市生活垃圾清扫、收集、运输、处理；固体废物治理（不含危险废物）；土壤污染治理；大气污染治理；经营其他无须行政审批即可经营的一般经营项目",
		"节能环保": "石油化工和煤化工脱硫龙头,具有化工、石化、医药行业的甲级工程设计资质,化工污水处理经验丰富;2017年环保工程总包收入1.1亿,45.54%。",
		"一带一路": "主要为石油化工、煤化工、精细化工、光热发电等行业的工程项目建设提供工程咨询、工程设计及工程总承包服务;公司先后承接了一些“一带一路”国家项目,提出了“两个市场、两条腿走路”的发展构想,拓展海外业务",
		"氢能源": "公司在碳四资源综合利用、煤炭高效清洁利用、高压加氢等工程技术领域具有较强的市场竞争力。",
		"年报预增": "公司预计2019-01-01到2019-12-31业绩：净利润7198.35万元至8398.08万元,增长幅度为80%至110%,上年同期业绩:净利润3999.08万元;"
	}
}