{
	"名称": "大金重工",
	"code": "002487",
	"全名": "大金重工股份有限公司",
	"地域": "辽宁省",
	"分类": "中盘股",
	"财务": "",
	"行业": "电力设备—风电设备",
	"业务": "风力发电设备制造。",
	"产品": "常规陆塔、大直径分片式陆塔、低风速柔性高塔、海塔、单桩、群桩、导管架、海上升压站等风电设备及相关零部件",
	"概念": "风电，绿色电力，振兴东北，高端装备，海工装备，融资融券，深股通",
	"概念y": "振兴东北-64%  装配式建筑-22%  甲醇-10%  互联网金融-7%  风电-6%  新能源-0%  海上风电-0%",
	"概念详情": {
		"风电": "公司专注于风电设备制造十余载，积累了丰富的生产制造经验，和较高的工艺技术水平，并凭借稳定的产品质量，高水平的装备设施能力，可靠的产品交付能力，成为了行业众多优质客户的战略供应商，并成长为全球风电装备制造产业的第一梯队企业。",
		"绿色电力": "公司官网显示：阜新彰武西六家子250MW风电项目一次性送电成功。本项目位于辽宁省阜新市彰武县境内，是大金重工股份有限公司目前自主投建的单体容量最大的风电场项目。项目共布置63台风力发电机组，采用4MW+3MW的混排方案，同时配套建设220kV升压站1座，集电线路10回，电网建设220kV外送线路1回。",
		"高端装备": "公司是一家从事电力重型装备钢结构产品的制造与销售的公司。",
		"海工装备": "2023年12月8日互动易：公司通过自建造船基地和专业化运输团队、自造风电海工装备、自有码头装运、自建特种运力运输，形成制造成本运输成本交期可控的独特竞争优势，有利于优先获得海外客户订单，保证交付安全及交货期限，降低运输成本，从而实现市场份额的逐步扩大。"
	},
	"亮点": "全球风电装备制造产业的第一梯队企业",
	"同业": "风电设备:  电气风电  海力风电  三一重能  飞沃科技  盘古智能  金风科技  天顺风能  湘电股份  运达股份  明阳智能  禾望电气  泰胜风能  金雷股份  威力传动",
	"概念z": "风电龙头",
	"备注": "",
	"链接": "",
	"概念x": "定增破发   风电",
	"概念xgb": {
		"风电": "国内首家风电海工产品出口到欧洲的企业；公司主要从事风电装备产品的生产和销售，新能源投资开发、建设和运营业务；公司主要生产及销售塔筒、管桩、导管架、浮式基础、过渡段等风电产品"
	}
}