{
	"名称": "汇洁股份",
	"code": "002763",
	"全名": "深圳汇洁集团股份有限公司",
	"地域": "广东省",
	"分类": "小盘股",
	"财务": "",
	"行业": "纺织服饰—服装家纺",
	"业务": "内衣人体工学研究、产品设计、生产制造、市场营销、品牌推广。",
	"产品": "文胸、内裤、保暖衣、OEM、睡衣",
	"概念": "跨境电商，电子商务，口罩",
	"概念y": "纺织服装-38%  人民币贬值-24%  化妆品-10%  流感-10%",
	"概念详情": {
		"跨境电商": "2021年6月25日投资者关系记录表：在跨境电商方面，针对北美消费者需求的品牌“UNDERSTANCE”于近日在北美上市，目前通过官网（加拿大独立站）向加拿大、美国用户销售，并有自己的海外仓。",
		"电子商务": "据2022年半年报显示：线上主要通过天猫、唯品会等电子商务平台向消费者销售公司产品；其中，曼妮芬、伊维斯、兰卓丽等主要品牌天猫渠道由公司自行运营，报告期内天猫渠道收入为27,470.2万元，占比21.66%；唯品会渠道委托运营服务商代运营，报告期内唯品会渠道收入为6,695.06万元，占比5.28%。",
		"口罩": "2020年2月28日，公司在互动平台表示，截止至目前，江西工厂正在改造十万级无尘无菌车间用于生产医用口罩，计划将于近期落成。在无菌车间落成之前，江西工厂利用现有部分流水线已生产了民用口罩。"
	},
	"亮点": "专业从事内衣人体工学研究、工艺技术研究，拥有八个主品牌",
	"同业": "内衣:  龙头股份  浪莎股份  爱慕股份  洪兴股份"
}