{
	"名称": "贝肯能源",
	"code": "002828",
	"全名": "新疆贝肯能源工程股份有限公司",
	"地域": "新疆维吾尔自治区",
	"分类": "小盘股",
	"财务": "",
	"行业": "石油石化—油服工程",
	"业务": "从事油气勘探和开发过程中的钻井工程技术服务及其他油田技术服务。",
	"产品": "钻井工程一体化、化工产品、检测、维修与租赁",
	"概念": "页岩气，俄乌冲突概念，天然气，参股银行，西部开发，新疆振兴，一带一路",
	"概念y": "参股银行-82%  一带一路-58%  油服-50%  页岩气-42%  天然气-16%  油改-12%  可燃冰-10%  西部开发-10%",
	"概念详情": {
		"天然气": "公司是一体化钻井工程技术服务商,国内天然气业务上,公司中标四川长宁页岩气;海外业务方面,已经中标乌克兰国家天然气钻采公司39亿元人民币(不含税)钻井工程服务项目;17年相关业务收入6.17亿元,主营占比超95%。",
		"页岩气": "公司是国内规模较大的、能够提供一体化钻井工程技术服务的独立油田服务供应商,可以提供钻井工程技术服务中的钻井、固井、钻井液、定向井、欠平衡等工程技术服务;曾表示,将大力开拓西南长宁页岩气等外部市场。",
		"新疆振兴": "公司位于新疆维吾尔自治区克拉玛依市，主要从事油气勘探和开发过程中的钻井工程技术服务及其他油田技术服务。",
		"一带一路": "公司主要从事油气勘探和开发过程中的钻井工程技术服务及其他油田技术服务，与新疆相邻的中西亚地区有丰富的能源资源，公司已尝试在哈萨克斯坦，伊朗开拓市场；2017年7月3日晚公告，公司前期在乌克兰天然气钻采合同投标的四个区块2017年至2019年三年钻井工程服务项目中标，以上4个区块合计中标金额约为5.09亿元，年均中标合同金额约1.69亿元。",
		"参股银行": "贝肯能源出资181.58万元，持股昆仑银行比例为0.025%。",
		"俄乌冲突概念": "俄乌冲突可能恶化俄罗斯油气出口前景，原油中枢或超预期。公司主要从事油气勘探和开发过程中的钻井工程技术服务及其他油田技术服务。"
	},
	"亮点": "国内规模较大的一体化钻井工程技术服务商",
	"同业": "钻井:  道森股份  如通股份  仁智股份"
}