{
	"名称": "迦南科技",
	"code": "300412",
	"全名": "浙江迦南科技股份有限公司",
	"地域": "浙江省",
	"分类": "小盘股",
	"财务": "",
	"行业": "机械设备—专用设备",
	"业务": "固体制剂设备的研发、生产和销售。",
	"产品": "粉体工艺设备系列、固体制剂设备系列、中药提取设备系列、流体工艺设备系列、智能仓储物流系统",
	"概念": "智能物流，工业4.0，创业板重组松绑",
	"概念y": "机器人-17%  物流骨干网-10%  医疗器械-6%  工业4.0-0%",
	"概念详情": {
		"工业4.0": "2017年年报公司表示，严格按照募集资金使用计划，尽快完成智能化中药提取生产线项目建设和制药装备工业4.0实验中心项目建设，通过上述项目建设改造公司生产流程及提升产品品质，一方面为产品研发提供实验平台和数据支持，并建立产品数据库；另一方面为制药企业提供制药工艺实验及制造设备选型实验等生产投入前的实验服务，形成产品与服务交互支撑的持续竞争优势。",
		"智能物流": "2020年5月15日路演称：公司将大力支持和依托控股子公司迦南飞奇在物流系统的技术积累和技术创新，为客户打造智能物流系统，提升客户物流效率和物流管理水平、降低物流成本。为客户构建智慧物流系统的透明工厂和智能配送体系，力争成为智慧物流行业的领军者和标准制定者之一。",
		"创业板重组松绑": "证监会发布重组新规，创业板放松借壳限制，公司是创业板小市值，近三年没被立案调查"
	},
	"亮点": "国内固体制剂工艺装备著名的设计生产厂家",
	"同业": "制药设备:  东富龙  诚益通  楚天科技"
}