{
	"名称": "利安隆",
	"code": "300596",
	"全名": "天津利安隆新材料股份有限公司",
	"地域": "天津市",
	"分类": "中盘股",
	"财务": "白马股",
	"行业": "化工—化学制品",
	"业务": "高分子材料抗老化技术及产品的研发、生产和销售。",
	"产品": "抗氧化剂、光稳定剂、U-PACK",
	"概念": "新材料概念，深股通",
	"概念y": "纤维新材料-10%  白马股-6%  新材料-5%",
	"概念详情": {
		"新材料概念": "公司产品应用于塑料，涂料，橡胶，化学纤维，胶黏剂五大高分子材料及其他特种高分子材料，公司与巴斯夫，LG化学，三菱化学，DSM，PPG，朗盛，科莱恩，旭化成，中石化等知名高分子材料制造企业形成了良好的合作关系，是上述企业的抗老化化学助剂供应商。"
	},
	"亮点": "高分子材料抗老化化学助剂领域拥有20年以上技术研发、应用经验",
	"同业": "化学助剂:   西陇科学   万盛股份   阳谷华泰   皇马科技   赞宇科技   宝莫股份   博汇股份   呈和科技   保立佳"
}