{
	"名称": "筑博设计",
	"code": "300564",
	"概念": "新股与次新股，非科创次新股，高送转预期，装配式建筑",
	"财务": "绩优股",
	"分类": "小盘股",
	"全名": "筑博设计股份有限公司",
	"地域": "西藏自治区",
	"行业": "建筑装饰—房屋建设",
	"业务": "从事建筑设计及其相关业务的设计与咨询",
	"产品": "居住建筑设计、城市型居住建筑、度假型居住建筑、公共建筑设计、医疗及养老建筑、办公建筑、教育建筑、文化建筑、城市综合体、超高层",
	"概念详情": {
		"新股与次新股": "公司上市日期为2019-11-08，主营为从事建筑设计及其相关业务的设计与咨询",
		"非科创次新股": "公司上市日期为2019-11-08，主营为从事建筑设计及其相关业务的设计与咨询",
		"装配式建筑": "公司在开展装配式建筑设计业务的过程中，充分发挥团队优势，以绿色建筑的理念贯穿整个设计过程，并利用BIM模型提高装配式建筑设计效率，对预制构件和室内装修设计进行精细化分析，实现预制构件的标准化设计，并以BIM技术对建造施工过程进行模拟，减少装配式建筑施工环节的碰撞。同时，以BIM技术为预制件在设计、生产、安装、运维阶段实现全流程的信息化管理。",
		"高送转预期": "公司每股资本公积金较高(1.32元)，每股未分配利润较高(3.54元)，且总股本较小(1亿股)，有较强的高送转潜力。"
	},
	"概念y": ""
}