{
	"名称": "佳发教育",
	"code": "300559",
	"全名": "成都佳发安泰教育科技股份有限公司",
	"地域": "四川省",
	"分类": "小盘股",
	"财务": "",
	"行业": "计算机—软件开发",
	"业务": "研发、生产、销售、实施具有自主知识产权和自主品牌的教育信息化产品并为用户提供相关服务。",
	"产品": "智慧招考产品系列、云巅智慧教育产品系列",
	"概念": "信创，国产软件，多模态AI，边缘计算，年报预增，人工智能，深股通，腾讯概念，虚拟数字人，在线教育，职业教育",
	"概念y": "职业教育-66%  在线教育-17%  业绩预增-16%  国产软件-13%  智慧城市-10%",
	"概念详情": {
		"信创": "2022年11月21日公司互动回复：公司作为智慧招考行业的领军企业，现标准化考点核心设备已可以全面国产化供货；网上巡查、作弊防控、身份验证、应急指挥和考务综合五大系统核心产品均已进行了系统应用软件（信创版）开发，并且推出了信创产品系列。",
		"国产软件": "最早从事国家教育考试信息化建设的企业之一;主要产品包括国家教育考试考务综合管理平台以及网上巡查、学业考试报名与管理、英语口语考试评测训练等教育考试考务信息化系统产品和包括走班排课、电子班牌、课堂生态、常态化考阅、教学资源云平台等“新高考”云巅智慧教育相关产品;18年信息服务-计算机应用收入3.90亿元,营收占比100%",
		"多模态AI": "2023年12月21日互动易回复：公司的AI大模型具备多模态能力，公司在理化生、英语听说、智慧体育等多业务场景中均融合使用了多模态技术。",
		"在线教育": "公司主营业务为研发，生产，销售具有自主知识产权和自主品牌的教育考试信息化产品并提供相关服务。主要产品包含教育考试考务管理与服务平台及网上巡查，应急指挥，身份认证，作弊防控等教育考试考务信息化系统产品。",
		"边缘计算": "边缘云计算是公司教育信息化解决方案中的一环，公司在业务中会用到相应的技术。",
		"职业教育": "公司主营业务为研发、生产、销售、实施具有自主知识产权和自主品牌的教育信息化产品并为用户提供相关服务，产品终端用户主要为各级教育管理机构和包括k12、中高职、高校在内的各类学校。",
		"人工智能": "据2021年年报：公司产品依托AI人工智能、机器视觉、大数据分析等先进技术，从教、学、管、练、评、考、研等多个方面有效提高学校教学和教学管理质量和效率。智慧体育产品为老师提供AI助教。",
		"腾讯概念": "据2021年半年报：公司联合腾讯教育，推出了新一代英语听说智能考试系统。",
		"虚拟数字人": "根据2023年12月11日互动易，公司在智慧考试和智慧教育都会有不同的细分产品用到人工智能技术。其中，公司在今年10月份发布的大模型AI能力应用主要有以下几项：AI命题助手，提升命题效率，关联海量题库，同时满足高质量原创试题和举一反三的教学需求；AI英语学习小助手，通过3D数智人老师的课标认知和引导能力，与学生一对一进行口语对练，个性化辅导，帮助学生提升发音和语法准确性；AI英语作文批改；AI生涯助手；AI虚拟仿真应用开发。目前，与AI大模型结合较为成熟的产品主要是英语听说产品，其基于大语音模型AI基座，将智能语音识别和语义分析等技术用在中学英语听说的“教、学、测、评、练、考”等环节。在完成产品的打磨后，后续",
		"年报预增": "公司预计2023-01-01到2023-12-31业绩：净利润13500万元至15500万元;增长幅度为95.79%至124.8%;上年同期业绩:净利润6895.07万元;。"
	},
	"亮点": "国家教育考试信息化建设与服务的国家高新技术企业",
	"同业": "教育信息化:  全通教育  鸿合科技  方直科技  新开普  竞业达  视源股份  国新文化  拓维信息  科大讯飞  *ST三盛  鸥玛软件"
}