{
	"名称": "鹏鹞环保",
	"code": "300664",
	"全名": "鹏鹞环保股份有限公司",
	"地域": "江苏省",
	"分类": "小盘股",
	"财务": "绩优股",
	"行业": "公用事业—水务Ⅱ",
	"业务": "提供环保水处理相关的研发、咨询与设计、设备生产及销售、工程承包、项目投资及运营管理等一站式服务。",
	"产品": "污水处理、污泥处理、工程承包、供水、环保设备销售、工程设计、咨询服务",
	"概念": "污水处理，固废处理，垃圾分类，生物疫苗",
	"概念y": "环保-100%  新冠病毒防治-100%  疫苗-100%  固废处理-100%  新冠疫苗-87%  新型病毒防治-80%  医药-18%  职业教育-10%  深股通-10%  苹果产业链-10%  垃圾分类-10%",
	"概念详情": {
		"固废处理": "2019年6月20日互动平台回复称公司现已进军固废资源化利用板块，在污泥处理、农业有机固体废弃物、餐厨垃圾以及湿垃圾等固废处理方面均有涉及。",
		"污水处理": "公司主营业务：提供环保水处理相关的研发、咨询与设计、设备生产与销售、工程承包、项目投资和运营。",
		"垃圾分类": "2019年6月20日互动平台回复称公司北京京环鹏鹞环境科技开发有限公司主要从事城市生活垃圾的清扫、收集、运输与处理，该子公司也采用了我司引进的YM菌高温好氧发酵技术。",
		"生物疫苗": "2020年2月6日公司在机构调研中称：我们投资的艾棣维欣是一家专业研究生物疫苗的公司，其首席科学家王宾教授是国内相关领域的顶尖专家，担任国家疫苗中心的主任，是中国新药评审的专家。艾棣维欣已经有了3-4个研究成果，包括呼吸道合胞病毒(RSV)预防性疫苗，I型糖尿病(T1D)治疗性疫苗等都已进入临床的研究。我们认为这家公司是一家具有相当研发能力的公司，另外与其合作的美国纳斯达克上市公司Inovio公司，也是一家良好资质的从事基因疫苗研究的公司。两家公司强强联手，基于DNA疫苗快速响应技术，在短期之内有望研发出新冠疫苗。",
		"送转填权": "公司分红明细为10转5股派0.65元(含税)，除权除息日为2020-05-27"
	},
	"亮点": "主营环境污染防治设备，水处理设备，玻璃钢制品",
	"同业": "水处理:  三达膜  泰和科技  碧水源  万邦达  博天环境  节能国祯  中环环保  联泰环保  中电环保  博世科  巴安水务  兴源环境  中持股份  清水源  中建环能  津膜科技  上海洗霸  京源环保  金科环境  德林海  上海凯鑫  金达莱  华骐环保  富淼科技  太和水  深水海纳  力源科技  唯赛勃"
}