{
	"名称": "盛德鑫泰",
	"code": "300881",
	"亮点": "在小口径高压锅炉用合金钢领域，在国内已经拥有一定的知名度",
	"概念": "注册制次新股，创投，核电，融资融券，特钢概念，新股与次新股",
	"同业": "",
	"分类": "小盘股",
	"全名": "盛德鑫泰新材料股份有限公司",
	"地域": "江苏省",
	"行业": "钢铁—钢铁",
	"业务": "各类工业用能源设备类无缝钢管的生产、研发和销售。",
	"产品": "不锈钢、合金钢、碳钢、钢格板",
	"概念详情": {
		"注册制次新股": "公司上市日期为2020-09-01，上市首五日不设涨跌幅限制，之后涨跌幅限制为20%。公司主营为各类工业用能源设备类无缝钢管的生产、研发和销售",
		"新股与次新股": "公司上市日期为2020-09-01，主营为各类工业用能源设备类无缝钢管的生产、研发和销售",
		"高送转预期": "公司每股资本公积金较高(4.42元)，每股未分配利润较高(1.62元)，且总股本较小(1亿股)，有较强的高送转潜力。"
	},
	"概念y": "钢铁-10%"
}