{
	"名称": "恒而达",
	"code": "300946",
	"亮点": "国内金属切削工具领域的龙头企业之一",
	"概念": "专精特新，工业母机，高端装备，融资融券",
	"同业": "3C设备:  泰嘉股份  新益昌  强瑞技术  大族数控  鼎泰高科  科瑞思  创世纪  福能东方  田中精机  宇环数控  华东重机  荣旗科技",
	"分类": "小盘股",
	"全名": "福建恒而达新材料股份有限公司",
	"地域": "福建省",
	"行业": "机械设备—通用设备",
	"业务": "金属切削工具、智能数控装备及高精度滚动功能部件的研发、生产及销售。",
	"产品": "模切工具、锯切工具、CNC全自动圆锯机、高速数控带锯床、柔性材料智能裁切机、直线导轨副",
	"概念y": "工业4.0-10%",
	"概念详情": {
		"专精特新": "专精特新“小巨人”企业是全国中小企业评定工作中最高等级、最具权威的荣誉称号，是指专注于细分市场、创新能力强、市场占有率高、掌握关键核心技术、质量效益优的排头兵企业，对于提升中小企业自身的竞争力，以及提升产业链、供应链稳定性和竞争力具有重大意义。公司已入选工信部专精特新小巨人企业名单。",
		"工业母机": "国内金属切削工具领域的龙头企业企业；公司主要从事模切工具、锯切工具、裁切工具等金属切削工具的研产销，核心产品之一重型模切工具的产销量与市占率均保持全球和行业首位，是国内双金属带锯条的产销龙头企业之一。",
		"高端装备": "据招股说明书：智能数控装备是公司基于在自动化专用装备制造方面的长期技术积累而开发，可与金属切削工具配套使用的高端装备。智能数控装备装有程序控制系统，能够按图纸要求的形状和尺寸自动加工，解决了复杂、精密、多品种零件的加工难题，是现代高端装备的发展方向。"
	}
}