{
	"名称": "森鹰窗业",
	"code": "301227",
	"亮点": "主营定制化节能铝包木窗",
	"概念": "装配式建筑，建筑节能，黑龙江自贸区，半年报预增，融资融券，碳中和，新股与次新股，注册制次新股",
	"同业": "门窗:  王力安防  江山欧派  海螺新材  嘉寓股份  罗普斯金",
	"分类": "小盘股",
	"全名": "哈尔滨森鹰窗业股份有限公司",
	"地域": "黑龙江省",
	"行业": "轻工制造—家居用品",
	"业务": "定制化节能铝包木窗研发、设计、生产及销售。",
	"产品": "节能铝包木窗、铝合金窗、幕墙及阳光房",
	"概念详情": {
		"装配式建筑": "2022年11月10日公司互动回复：公司产品作为部品化建筑外围护结构组件，可应用于装配式建筑领域，以及其他传统建造方式的建筑领域。截至本回复之日，公司产品已在多个不同装配率要求的装配式建筑项目中应用。",
		"建筑节能": "公司始终致力于研发制造拥有超低传热系数建筑外窗，从结构研发、材质选择、细节工艺、成装核验、成品安装等各环节的精益求精保证整窗密封性能。至今，累计近20款窗品通过德国PHI认证，可适用于零碳建筑，成功服务中国近百项被动式超低能耗绿色建筑，并参与制定多地建筑节能标准，助力推动中国零碳建筑发展。",
		"黑龙江自贸区": "公司地址是黑龙江省哈尔滨市南岗区王岗镇新农路9号",
		"注册制次新股": "公司上市日期为2022-09-26，上市首五日不设涨跌幅限制。公司主营为定制化节能铝包木窗研发、设计、生产及销售。",
		"新股与次新股": "公司上市日期为2022-09-26，主营为定制化节能铝包木窗研发、设计、生产及销售。",
		"碳中和": "2022年9月27日公司互动回复：国务院印发的《2030年前碳达峰行动方案》亦提出，加强木竹建材等低碳建材产品研发应用。公司以高效保温隔热性能的节能铝包木窗作为主要产品，主要产品属于《战略性新兴产业分类（2018）》中的“7.1.5绿色节能建筑材料制造”之“铝木复合门窗”。此外，公司以P120系列产品为代表的被动式节能铝包木窗相比标准窗具有更强的保温隔热能力，能够满足国内超低能耗建筑对窗的性能要求，能够用于被动式建筑。",
		"半年报预增": "公司预计2023-01-01到2023-06-30业绩：净利润3600.00万元至4650.00万元,增长幅度为50.10%至93.88%,上年同期业绩:净利润2398.38万元;。"
	}
}