{
	"名称": "中汽股份",
	"code": "301215",
	"亮点": "一家集汽车试验场投资、运营、管理为一体的汽车服务公司",
	"概念": "央企国企改革，比亚迪概念，国企改革，人脸识别，融资融券，蔚来汽车概念，新股与次新股，虚拟现实，中字头股票，注册制次新股",
	"同业": "检测认证:  国缆检测  思科瑞  西测测试  建科股份  谱尼测试  开普检测  安车检测  信测标准  联测科技  实朴检测  华测检测  电科院  国检集团  中国汽研  钢研纳克  广电计量",
	"分类": "小盘股",
	"全名": "中汽研汽车试验场股份有限公司",
	"地域": "江苏省",
	"行业": "汽车—汽车服务",
	"业务": "通过构建汽车场地试验环境和试验场景，为汽车整车生产企业、汽车检测机构、汽车底盘部件系统企业以及轮胎企业等客户提供场地试验技术服务。",
	"产品": "场地试验技术服务、检测业务",
	"概念详情": {
		"央企国企改革": "公司大股东或者控股股东或者实控人涉及央企。",
		"比亚迪概念": "公司场地试验技术服务需求的汽车整车生产企业、汽车检测机构、汽车底盘部件系统等业务方面与比亚迪达成合作。",
		"国企改革": "公司属于国有企业。公司的最终控制人为国务院国有资产监督管理委员会。",
		"新股与次新股": "公司上市日期为2022-03-08，主营为通过构建汽车场地试验环境和试验场景，为汽车整车生产企业、汽车检测机构、汽车底盘部件系统企业以及轮胎企业等客户提供场地试验技术服务。",
		"注册制次新股": "公司上市日期为2022-03-08，上市首五日不设涨跌幅限制，之后涨跌幅限制为20%。公司主营为通过构建汽车场地试验环境和试验场景，为汽车整车生产企业、汽车检测机构、汽车底盘部件系统企业以及轮胎企业等客户提供场地试验技术服务。",
		"人脸识别": "目前公司应用了人脸识别技术，加装车载OBU等，主要用于车辆识别及场内准入等内部运营管理。",
		"虚拟现实": "公司已完成了强化耐久路三维数字化虚拟路面建设以及舒适性能路纵断面二维数字化路面建设工作，并协同搭建5G高精度定位车辆运行监控管理系统。未来公司将利用数字孪生等虚拟测试技术，搭建更多数字化虚拟测试场景，全面涵盖测试场地（道路及其周边环境地理信息）、交通标识变化和交通流（车辆、行人、障碍），模拟天气和光照变化、路面变化、测试车辆运行等，为客户提供实景测试场地和虚拟试验场相结合的场地试验技术服务，加速车辆试验研发过程。",
		"中字头股票": "公司为中字头股票，公司实控人为国资委或中央国有企业或中央国家机关。"
	}
}