{
	"名称": "青山纸业",
	"code": "600103",
	"全名": "福建省青山纸业股份有限公司",
	"地域": "福建省",
	"分类": "中盘股",
	"财务": "",
	"行业": "轻工制造—造纸",
	"业务": "制浆造纸、纸箱及纸袋制造、医药、光电子、林业领域的生产、设计和销售。",
	"产品": "“青山牌”系列伸性纸袋纸、精制牛皮包装纸、溶解浆、竹木浆、风油精",
	"概念": "共封装光学(CPO)，海峡两岸，创投，5G，国企改革，沪股通，数据中心，一带一路",
	"概念y": "中证1000-100%  林业-100%  海峡西岸-88%  造纸-60%  林场改革-39%  智慧林业-11%  超高清视频-10%  人造肉-10%  参股新三板-10%  军工-9%  人民币升值-9%",
	"概念详情": {
		"共封装光学(CPO)": "2025年半年报，子公司深圳恒宝通实现扭亏为盈，400G产品已进入小批量试产阶段，800G光模块已完成设计，进入样品试制阶段。",
		"海峡两岸": "公司地处福建省三明市，主要从事竹木浆、浆粕、纸袋纸、纸制品、光电子产品、医药产品、林木产品等产品产销及其贸易经营。",
		"创投": "2024年11月29日互动易回复，公司参投福建省国资融合股权投资合伙企业，基金总规模20亿元人民币，一期规模5亿元人民币，公司为有限合伙人，出资5,000万元，占出资总额10%。",
		"5G": "公司控股子公司恒宝通光电子股份有限公司主营光通信模块及组件产品的研发、生产及销售，系国家级高新技术企业。产品主要应用于移动通信领域，为全球大型模拟半导体设备供应厂商Avago逾十年的供应商。",
		"国企改革": "公司属于国有企业。公司的最终控制人为福建省人民政府国有资产监督管理委员会。",
		"一带一路": "2023年9月18日互动易回复：公司子公司恒宝通于2019年在马来西亚新山市投资建设了光电模块生产制造基地，目前马来西亚恒宝通公司生产经营正常开展。",
		"数据中心": "2025年半年报，公司光电子产业深化自有品牌市场布局，加大数据中心，AI智算中心市场开拓力度，实现扭亏为盈。子公司深圳恒宝通实现扭亏为盈，400G产品已进入小批量试产阶段，800G光模块已完成设计，进入样品试制阶段，电口产品销售同比实现大幅增长，继续保持64G产品唯一供应商优势，销量稳中有升。"
	},
	"亮点": "福建国资委旗下，已构建“林-浆-纸”产业链，主导产品伸性纸袋纸在水泥包装领域占据龙头地位",
	"同业": "造纸:  太阳纸业  晨鸣纸业  山鹰国际  岳阳林纸  博汇纸业  景兴纸业  荣晟环保  华泰股份  宜宾纸业  凯恩股份  美利云",
	"概念xgb": {
		"造纸": "综合性造纸上市公司，主导产品纸袋纸系列产品国内市占率第一；公司主要从事竹木浆、浆粕(溶解浆)、纸袋纸、纸制品、光电子产品、医药产品、林木产品等产品产销及其贸易经营，主要产品为“青山牌”系列伸性纸袋纸、牛皮包装纸、溶解浆等产品",
		"强势人气股": "题材：光通信；时间：25年9月2日至今，9天6板\n",
		"光通信": "子公司深圳市恒宝通为中国器件与辅助设备设备和原材料最具竞争力企业之一，提供从155Mb/s到400Gb/s的全系列产品，包括QSFP-DD、QSFP56、QSFP28、QSFP+、SFP+、SFP等，400G光模块处于产品优化和产线建设阶段，800G产品处于技术预研阶段",
		"林业": "综合性造纸上市公司；公司是国内率先发展“林纸一体化”的龙头企业，拥有林木资产面积约35万亩，蓄积量约210万立方米左右",
		"军民融合": "参股公司（持股20%）福建海峡军民融合后勤（食品）保障有限公司 ，参与建设福建省军民融合后勤（食品）保障项目；公司与北京工商大学合作，采用对方技术生产人造肉，产品初步供应军方，满足单兵野外训练等需求",
		"军工": "参股公司（持股20%）福建海峡军民融合后勤（食品）保障有限公司 ，参与建设福建省军民融合后勤（食品）保障项目；公司与北京工商大学合作，采用对方技术生产人造肉，产品初步供应军方，满足单兵野外训练等需求",
		"人造肉": "公司与北京工商大学人造肉领域资深副教授李建团队，达成深度合作共识，双方在务实态度上开启“人造肉”相关科研与产品转化的工作，预计相关产品在2020年底全面上市"
	},
	"概念x": "造纸   强势人气股   光通信   林业   军民融合   军工   人造肉"
}