{
	"名称": "盛和资源",
	"code": "600392",
	"全名": "盛和资源控股股份有限公司",
	"地域": "四川省",
	"分类": "中盘股",
	"财务": "所属申万行业：稀有金属",
	"行业": "有色金属—小金属",
	"业务": "稀土矿采选、冶炼分离、金属加工以及锆钛矿选矿业务。",
	"产品": "稀土矿、稀土冶炼分离、稀土金属、锆钛业务",
	"概念": "稀土永磁，小金属概念，苹果概念，标普道琼斯A股，参股保险，国企改革，沪股通，融资融券",
	"概念y": "中证500-100%  稀土-73%  稀土-58%  融资融券-32%  稀土磁材-27%  贵金属-26%  锗-15%  央企国资改革-14%  稀土永磁-14%  自贸区-10%  参股保险-10%  MSCI-10%  苹果产业链-10%  海南自由贸易港-10%  沪股通-8%  低碳-0%",
	"概念详情": {
		"稀土永磁": "公司与美国芒廷帕斯矿山团队合作，目前全年产量已超过3万吨REO，已成为中国之外最大的稀土矿山，产品全部由公司销售到国内处理。公司在美国矿山项目公司拥有9.99%的优先股和部分认股权证。公司下属赣州步莱铽新资源有限公司是专业从事稀土钕铁硼、荧光粉废料回收的企业，拥有30余项专利技术，年处理稀土废料约6000吨左右。",
		"小金属概念": "公司的主要产品包括稀土精矿、稀土氧化物、稀土盐、稀土金属、稀土高效催化剂及分子筛、锆英砂、钛精矿、金红石、独居石等。",
		"苹果概念": "盛和资源官网公告显示，盛和资源入选AppleInc.供应商清洁能源计划，承诺采用100%清洁能源为与Apple相关的生产制造供电。",
		"参股保险": "2017年2月22日晚间公告，近日保监会正式同意华贵人寿保险股份有限公司开业，注册资本为10亿元。其中，公司出资5000万元，占其股份总数的5%。",
		"标普道琼斯A股": "2018年12月1日，指数编制公司标普道琼斯宣布，将部分中国A股纳入其全球指数体系，分类基本为新兴市场。2019年9月，标普道琼斯新兴市场指数以25%的纳入因子纳入A股。",
		"国企改革": "公司属于国有企业。公司的最终控制人为中华人民共和国财政部。"
	},
	"亮点": "主要产品为稀土金属、稀土氧化物、锆英砂、钛精矿等",
	"同业": "稀土:  北方稀土  中国稀土  广晟有色"
}