{
	"名称": "外服控股",
	"code": "600662",
	"全名": "上海外服控股集团股份有限公司",
	"地域": "上海市",
	"分类": "中盘股",
	"财务": "所属申万行业：公交Ⅱ",
	"行业": "社会服务—专业服务",
	"业务": "综合人力资源服务,包括人事管理服务、薪酬福利服务、招聘及灵活用工服务、业务外包服务等。",
	"产品": "出租汽车、汽车租赁、汽车服务、旅游服务、房产",
	"概念": "网约车，阿里巴巴概念，智能交通，旅游，融资融券，上海国资改革，统一大市场",
	"概念y": "出租车-100%  中证1000-100%  上海国企-64%  公共交通-62%  融资融券-35%  网约车-27%  迪士尼-22%  阿里巴巴-11%  汽车销售-10%  国企改革-10%  金融IC卡-10%  共享经济-10%  旅游-10%  支付宝-7%  智能交通-6%",
	"概念详情": {
		"网约车": "公司推出有两款适应智能通讯时代的最新免费软件“强生叫车”和“强生路况”。子公司强生科技开发了适用于安卓系统的智能车载终端，支持第三方软件在车载终端上的应用。2014年3月份，“快的”，“嘀嘀”两打车软件率先与强生出租调度平台技术对接。",
		"上海国资改革": "公司最终控制人为上海市国有资产监督管理委员会，属于地方国资委，其最终持有公司股票47401.3万股，占总股本的45%。",
		"智能交通": "2012年年报披露，控股子公司强生智能导航公司(公司占67.3%)开发的“一键通”叫车自助终端、“实时路况行车引导系统”已投入使用。2013年3月，公司推出两款适应智能通讯时代的最新免费软件“强生叫车”和“强生路况”。2013年中报披露，公司连续推出了手机叫车、微信叫车、一键通叫车等适应移动互联网时代的新型叫车方式，确保了强生电调市场的龙头地位；强生智能导航公司自主研发的“强生路况”系统，用户数量也已初具规模，逐步形成了广告发布的商业渠道。2014年3月，“快的”、“嘀嘀”两大打车软件率先与强生出租调度平台技术对接。",
		"阿里巴巴概念": "17年9月,子公司强生出租汽车公司与支付宝钱包达成战略合作,公司旗下一万多辆出租车将全线支持支付宝支付车费为乘客提供更多样、更贴近时代的服务。"
	},
	"亮点": "国内人力资源服务龙头企业",
	"同业": "公路客运:  大众交通  锦江在线  三峡旅游  龙洲股份  海汽集团  *ST德新  富临运业  江西长运  交运股份"
}