{
	"名称": "神马股份",
	"code": "600810",
	"全名": "神马实业股份有限公司",
	"地域": "河南省",
	"分类": "中盘股",
	"财务": "所属申万行业：化学纤维",
	"行业": "基础化工—化学纤维",
	"业务": "尼龙66工业丝、帘子布、尼龙66切片、己二酸、尼龙6切片、尼龙6民用丝等产品的研发、生产与销售。",
	"产品": "工业丝、帘子布、尼龙66切片、己二酸、双酚A、PC、环己烷、阻燃纤维、原液色丝、尼龙6切片、尼龙6民用丝",
	"概念": "光伏建筑一体化，国企改革，回购增持再贷款概念，股权转让(并购重组)，沪股通，军工，融资融券",
	"概念y": "晋陕豫-100%  尼龙-90%  己二酸-83%  轮胎-19%  工程塑料-19%  循环经济-17%  丁二醇-15%  己内酰胺-15%  氯碱-12%  河南国资-12%  化纤-8%  聚氯乙烯-1%",
	"概念详情": {
		"光伏建筑一体化": "神马股份下属单位帘子布发展公司6MW屋顶发电项目成功入选国家第二批智能光伏试点示范项目，成为河南省唯一入选项目。",
		"国企改革": "公司属于国有企业。公司的最终控制人为河南省人民政府国有资产监督管理委员会。",
		"回购增持再贷款概念": "2024年11月15日公告，公司拟回购金额不低于人民币15,000万元，不超过人民币30,000万元，回购价格不超过人民币10.77元/股。公司回购资金来源于自有资金及中国工商银行河南省分行提供的专项贷款，专项贷款金额不超过2.1亿元。",
		"军工": "公司积极调整产品结构，加快向军工和高端领域的拓展，与DB项目、地毯丝、尼龙66细旦特种纤维项目合作方深化交流。研发差异化产品，开发航胎产品，完成了中橡曙光样布试验，开发的产品已在歼10、歼15、运20等军工行业使用。",
		"股权转让(并购重组)": "据2025年9月25日公告：2025年9月25日，神马实业股份有限公司(以下称公司)接到控股股东中国平煤神马控股集团有限公司(以下简称中国平煤神马集团)通知，根据河南省委、省政府决定，中国平煤神马集团拟与河南能源集团有限公司实施战略重组。"
	},
	"亮点": "河南国资委所属中国平煤神马集团旗下，实现了尼龙的一体化全流程研发，工业丝帘子布被评为制造业单项冠军产品",
	"同业": "锦纶:  台华新材  华鼎股份  恒申新材",
	"概念xgb": {
		"回购": "25年9月，拟以1亿元-2亿元回购股份，回购股份价格不超过人民币14.97元/股",
		"锦纶（尼龙）": "中国聚酰胺行业的领军企业之一，尼龙66产能规模位居全球前五；公司形成了以尼龙66盐和尼龙66盐中间产品、尼龙66切片、工业丝、帘子布等主导产品为支柱、以原辅材料等产品为依托的格局；“神马”牌工业丝、帘子布产品已出口到全球40多个国家和地区，是米其林、普里斯通等世界著名轮胎集团的全球采购供应商；尼龙66切片年总产能达25万吨，2024年新建1000吨/年中试生产线，项目研发成功后，新增尼龙66差异化、功能性细旦纤维1000吨/年产能",
		"国企改革": "河南省国资委旗下；主要从事尼龙66工业丝、帘子布、切片、己二酸等产品的生产与销售",
		"河南国企改革": "河南省国资委旗下；主要从事尼龙66工业丝、帘子布、切片、己二酸等产品的生产与销售"
	},
	"概念x": "回购   锦纶（尼龙）   国企改革   河南国企改革"
}