{
	"名称": "新奥股份",
	"code": "600803",
	"全名": "新奥天然气股份有限公司",
	"地域": "河北省",
	"分类": "大盘股",
	"财务": "所属申万行业：综合Ⅱ",
	"行业": "公用事业—燃气Ⅱ",
	"业务": "天然气零售业务，综合能源业务，天然气生产,批发和直销业务，延伸业务，工程施工及安装业务，煤炭及甲醇业务。",
	"产品": "工程施工与安装、综合能源销售及服务、自产煤炭、自产甲醇、化工贸易、生物制药",
	"概念": "天然气，氢能源，雄安新区，MSCI概念，半年报预增，沪股通，甲醇，融资融券",
	"概念y": "中证1000-100%  油改-26%  二甲醚-24%  登革热-24%  登革热-24%  融资融券-24%  杀虫剂-20%  生物柴油-16%  天然气-16%  海藻炼油-16%  氢燃料电池-13%  油气-12%  沪股通-10%  氢能-10%  智慧城市-10%  虫害防治-10%  甲醇-4%  农村电商-2%  农药-1%  生物燃料-0%",
	"概念详情": {
		"天然气": "位于山西的全资子公司沁水新奥是公司LNG产品产销主体,以煤层气为原料生产LNG;目前运营两套煤层气制LNG装置,LNG产能约为10万吨,LNG储能300万吨;持有澳大利亚第二大油气上市公司Santos1007%股权,总证实储量4.85亿桶油当量,为Santos第一大股东;持有中海油北海45%股权;17年相关业务收入3.27亿元,主营占比小于5%;18年10月,LNG接收站一期正式投运",
		"氢能源": "公司控股子公司新能能源20万吨/年稳定轻烃项目LNG装置打通催化气化、加氢气化两项核心煤气化技术工艺流程，并于2018年12月投料试车并产出合格产品。",
		"雄安新区": "2020年8月6日互动平台回复：公司能源工程业务在雄安有一个在建燃气管线项目。"
	},
	"亮点": "具有创新力和竞争力的天然气上游供应商",
	"同业": "油气生产:   新潮能源   洲际油气   蓝焰控股   ST中天   广汇能源   东华能源   首华燃气"
}