{
	"名称": "杭州银行",
	"code": "600926",
	"全名": "杭州银行股份有限公司",
	"地域": "浙江省",
	"分类": "超大盘股",
	"财务": "破净股，二线蓝筹",
	"行业": "银行—城商行Ⅱ",
	"业务": "为城乡中、小企业客户及居民家庭提供全面的商业银行产品及服务。",
	"产品": "交易银行、投资银行、科创金融、绿色金融、小微金融、财富管理、消费信贷、网络金融、金融市场、金融同业、资产托管、资产管理、线上渠道、线下渠道、客服中心",
	"概念": "高股息精选，MSCI概念，标普道琼斯A股，沪股通，融资融券",
	"概念y": "融资融券-30%  国企改革-10%  浙江国企改革-10%  长三角一体化-10%  沪股通-9%  MSCI-9%  银行-8%  沪深300-6%  杭州亚运会-5%",
	"概念详情": {
		"高股息精选": "杭州银行连续3年股息率分别为：2.73%，3.06%，5.19%",
		"MSCI概念": "2017年6月20日，MSCI（明晟）宣布，将中国A股纳入MSCI新兴市场指数，促进中国境内市场与全球资本市场的进一步融合。MSCI公布2020半年度指数审议结果，仍维持A股20%的纳入因子，仅对成分股做以调整。",
		"标普道琼斯A股": "2018年12月1日，指数编制公司标普道琼斯宣布，将部分中国A股纳入其全球指数体系，分类基本为新兴市场。2019年9月，标普道琼斯新兴市场指数以25%的纳入因子纳入A股。"
	},
	"亮点": "富有特色的科技文创和绿色金融体系，打造新型智慧银行",
	"同业": ":  ",
	"概念x": "长三角一体化   银行   破净股   MSCI   大金融",
	"概念xgb": {
		"长三角一体化": "位于杭州；长三角城商行之一，主要布局杭州及浙江市场，基本实现浙江省内机构全覆盖",
		"银行": "长三角城商行之一，主要布局杭州及浙江市场，基本实现浙江省内机构全覆盖；稳步推进“数智杭银”建设",
		"大金融": "长三角城商行之一，主要布局杭州及浙江市场，基本实现浙江省内机构全覆盖；稳步推进“数智杭银”建设"
	}
}