{
	"名称": "宁波港",
	"code": "601018",
	"全名": "宁波舟山港股份有限公司",
	"地域": "浙江省",
	"分类": "大盘股",
	"财务": "二线蓝筹",
	"行业": "交通运输—航运港口",
	"业务": "集装箱、铁矿石、原油、煤炭、液化油品、粮食、矿建材料及其他货种港口装卸及相关业务,同时从事综合物流、贸易销售等其他业务。",
	"产品": "集装箱装卸、铁矿石装卸、原油装卸、一般货物装卸、综合物流",
	"概念": "自由贸易港，一带一路，MSCI概念，标普道琼斯A股，分拆上市意愿，杭州湾大湾区，沪股通，融资融券",
	"概念y": "沪深300-100%  中证100-100%  舟山自贸区-40%  港口-13%  长三角一体化-10%  证金持股-10%  融资融券-10%  浙江国企改革-10%  MSCI-10%  上海自由贸易港-10%  国企改革-10%  长三角港口-9%  舟山新区-8%  中日韩自贸区-8%  集装箱-7%  长江经济带-5%  浙江自贸区-3%  上海国际金融中心建设-2%  一带一路-1%  海洋经济-0%",
	"概念详情": {
		"自由贸易港": "十九大报告提出，赋予自由贸易试验区更大改革自主权，探索建设自由贸易港。记者注意到，目前内地城市中尚无自由贸易港，不过，上海自贸试验区已经提出建设自由贸易港区。在十九大开幕会后，一些地方也表示要加快相关工作步伐。据当地媒体报道，浙江自贸试验区综合服务中心主任黄义盛表示，在赋予自贸试验区建设更大改革自主权、探索建设自由贸易港，舟山在这方面已经先行一步。",
		"一带一路": "公司是全国最大码头运营商之一，货物吞吐量和集装箱吞吐量在我国港口行业居于领先地位，拥有完备集装箱、矿石、原油、煤炭、液体化工产品处理体系，能提供上述五大基础货物装卸服务。",
		"证金持股": "截止2020年09月30日,中国证券金融股份有限公司持有宁波港39439.29万股。",
		"MSCI概念": "2017年6月20日，MSCI（明晟）宣布，将中国A股纳入MSCI新兴市场指数，促进中国境内市场与全球资本市场的进一步融合。MSCI公布2020半年度指数审议结果，仍维持A股20%的纳入因子，仅对成分股做以调整。",
		"标普道琼斯A股": "2018年12月1日，指数编制公司标普道琼斯宣布，将部分中国A股纳入其全球指数体系，分类基本为新兴市场。2019年9月，标普道琼斯新兴市场指数以25%的纳入因子纳入A股。"
	},
	"亮点": "货物吞吐量和集装箱吞吐量持续保持全球港口前列",
	"同业": "港口:  上港集团  招商港口  青岛港  广州港  秦港股份  唐山港  天津港  盐田港  厦门港务  辽港股份"
}