{
	"名称": "陕西黑猫",
	"code": "601015",
	"全名": "陕西黑猫焦化股份有限公司",
	"地域": "陕西省",
	"分类": "中盘股",
	"财务": "破净股，绩差股",
	"行业": "煤炭—焦炭Ⅱ",
	"业务": "煤焦化及化工产品的生产和销售。",
	"产品": "焦炭、焦油、甲醇、合成氨、LNG、BDO、精煤、中煤",
	"概念": "煤炭概念，天然气，煤化工，标普道琼斯A股，沪股通，甲醇，融资融券，污水处理",
	"概念y": "中证1000-100%  动力煤-41%  陕西自贸区-41%  焦炭-36%  煤炭-20%  己内酰胺-18%  沪股通-14%  光伏-10%  甲醇-8%  煤焦油-5%  煤化工-5%  天然气-4%",
	"概念详情": {
		"煤炭概念": "陕西省最大的独立焦化企业，产品为焦化产品和化工产品，陕西省发改委确认的“循环经济试点企业”；19年焦炭销量480.26万吨，焦炭收入78.27亿元，主营占比83.37%。",
		"天然气": "公司采用的焦炉煤气制LNG，主要进入障碍在于焦化企业焦炭产能达到行业准入规模后，焦炉煤气制LNG才能形成一定规模，同时焦化企业需掌握焦炉煤气甲烷化制LNG技术。公司LNG产品2021年产量为13.89万吨，据国家统计局数据，2021年全国LNG产量约为2,053亿立方米，公司所占市场份额较小。",
		"煤化工": "公司的主要产品有焦炭、甲醇、粗苯、煤焦油、液化天然气、合成氨、LNG。",
		"标普道琼斯A股": "2018年12月1日，指数编制公司标普道琼斯宣布，将部分中国A股纳入其全球指数体系，分类基本为新兴市场。2019年9月，标普道琼斯新兴市场指数以25%的纳入因子纳入A股。",
		"污水处理": "21年4月20日公告披露，公司拟收购关联方“黄河矿业所持韩城市西昝工业园区污水处理有限公司100%股权。标的公司主营业务为污水处理及其再生利用。"
	},
	"亮点": "我国煤焦化循环经济领域的领先企业",
	"同业": "炼焦:  ST安泰  山西焦化  金能科技  云煤能源  宝泰隆  开滦股份  美锦能源  云维股份"
}