{
	"名称": "通用股份",
	"code": "601500",
	"全名": "江苏通用科技股份有限公司",
	"地域": "江苏省",
	"分类": "小盘股",
	"财务": "",
	"行业": "汽车—汽车零部件",
	"业务": "轮胎产品的研发、生产和销售。",
	"产品": "短途工矿型轮胎、中短途承载型轮胎、中长途公路运输型轮胎、轻卡型轮胎、PCR（家用轿车轮胎）、SUV（城市越野轮胎）、AT/MT(越野轮胎）、LT（商用载重胎）",
	"概念": "新材料概念，一带一路",
	"概念y": "中证1000-100%  一带一路-80%  车联网-51%  轮胎-29%  石墨烯-10%  纺织服装-10%",
	"概念详情": {
		"一带一路": "2019年5月6日互动平台回复：在国际化方面，公司通过研发、生产、营销、人才四个方面积极布局，抢抓一带一路机遇，目前正在泰国建设生产基地，计划将于2019年12月试生产，同时也将进一步拓展一带一路国家营销渠道，以及建立国际研发设计室，更好地贴近市场服务。",
		"车联网": "公司参股的江苏天安智联科技股份有限公司是一家为客户提供物联网整体解决方案以及配套软硬件的高科技企业，集研发、生产、销售、服务为一体，主要产品包括智能车载终端产品、定制化物联网专属平台产品及其他软件产品等。",
		"新材料概念": "2018年公司年报披露：公司注重创新能力的持续提升，在产学研方面推进与北京化工大学、中科院力学研究所协同创新的低滚阻绿色轮胎项目取得阶段性成果。在新材料应用方面，公司通过研究杜仲橡胶、石墨烯、超高强度钢丝帘线等材料的产业化应用，促使轮胎更加绿色环保，性能更加优异。其中在业内首次实现了合成型杜仲橡胶（TPI）在全钢子午胎中连续化生产，大幅提升产品耐磨性和抗切割性能，通过科技成果鉴定，综合技术达到国际先进水平；同时公司产品不断升级，通过中橡协绿色标签认证19个,位居中橡协发布的C3标签类榜首。",
		"参股新三板": "公司参股天安智联。天安智联于2015年3月在新三板挂牌，代码832046，是成熟的车联网服务集成商，专注于车联网智能终端软硬件和车联网技术服务平台研发。"
	},
	"亮点": "中国卡车轮胎替换市场的领军企业之一",
	"同业": "轮胎:  玲珑轮胎  三角轮胎  赛轮轮胎  青岛双星  贵州轮胎  风神股份  森麒麟  SST佳通  华谊集团"
}