{
	"名称": "建设银行",
	"code": "601939",
	"全名": "中国建设银行股份有限公司",
	"地域": "北京市",
	"分类": "超大盘股",
	"财务": "破净股，权重股，一线蓝筹",
	"行业": "银行—国有大型银行Ⅱ",
	"业务": "银行业及有关的金融服务。",
	"产品": "公司金融业务、个人金融业务、资金资管业务、其他业务",
	"概念": "高股息精选，同花顺中特估100，证金持股，沪股通，跨境支付(CIPS)，融资融券",
	"概念y": "沪深300-100%  中央汇金-70%  国际板-49%  支付宝-22%  沪港通结算银行-14%  证金持股-10%  央企国资改革-10%  融资融券-10%  MSCI-10%  沪股通-10%  银行-4%",
	"概念详情": {
		"高股息精选": "建设银行最近3年的股息率分别为：6.91%，6.14%，4.58%",
		"同花顺中特估100": "2022年11月21日，金融街论坛年会上提出：“探索建立具有中国特色的估值体系，促进市场资源配置功能更好发挥”。之后被分析师总结为“中国特色估值体系”，简称“中特估”。本概念综合上市公司行业地位、估值、市盈率、净利润、券商研报点评等多个要素甄选。更新频率为每月更新。",
		"证金持股": "公司前十大流通股东中包含中央汇金资产管理有限责任公司或中国证券金融股份有限公司。",
		"跨境支付(CIPS)": "CIPS是我国重要的金融市场基础设施，在助力人民币国际化等方面发挥着重要作用。公司是首批直接参与者之一。"
	},
	"亮点": "中国第二大银行",
	"同业": "银行:  工商银行  农业银行  中国银行  交通银行  招商银行  民生银行  兴业银行  浦发银行  中信银行  华夏银行  平安银行  光大银行  邮储银行",
	"概念x": "高股息   银行   破净股   大金融",
	"概念xgb": {
		"高股息": "中证红利指数成份股，现金股息率高、分红较为稳定",
		"银行": "六大行之一；中国第二大商业银行，拥有业内首家全资金融科技子公司，开设国内首家“无人银行”",
		"大金融": "六大行之一；中国第二大商业银行，拥有业内首家全资金融科技子公司，开设国内首家“无人银行”"
	}
}