{
	"名称": "亚普股份",
	"code": "603013",
	"全名": "亚普汽车部件股份有限公司",
	"地域": "江苏省",
	"分类": "中盘股",
	"财务": "",
	"行业": "汽车—汽车零部件",
	"业务": "从事储能系统产品、热管理系统产品的研发、制造、销售和服务。",
	"产品": "燃油系统（含混动汽车高压燃油系统）、电池包壳体、储能电池包箱体、燃料电池储氢系统、极寒加温系统、风道",
	"概念": "新能源汽车，比亚迪概念，燃料电池，标普道琼斯A股，储能，国企改革，沪股通，氢能源，央企国企改革，专精特新",
	"概念y": "新股与次新股-45%  汽车零部件-30%  央企国资改革-10%  氢能-10%  国六排放标准-10%  新能源汽车-10%  氢燃料电池-10%",
	"概念详情": {
		"新能源汽车": "公司高度关注新能源汽车相关研究，并正在推进氢燃料供给系统的研发。",
		"比亚迪概念": "公司取得比亚迪DMII车型燃油箱配套订单。",
		"燃料电池": "2019年4月18日公司在投资者互动平台表示，氢能作为车用燃料，是一种零污染燃料。公司高度关注并正在推进氢燃料供给系统的研发，通过研究氢燃料供给系统，能够利用公司现有平台，向顾客提供不同的燃料系统。",
		"标普道琼斯A股": "2018年12月1日，指数编制公司标普道琼斯宣布，将部分中国A股纳入其全球指数体系，分类基本为新兴市场。2019年9月，标普道琼斯新兴市场指数以25%的纳入因子纳入A股。",
		"氢能源": "公司自主研发的国内首套侧挂式储氢系统已搭载“成渝氢走廊”氢燃料电池物流车并于2021年11月30日正式发车。",
		"央企国企改革": "公司大股东或者控股股东或者实控人涉及央企。",
		"专精特新": "专精特新“小巨人”企业是全国中小企业评定工作中最高等级、最具权威的荣誉称号，是指专注于细分市场、创新能力强、市场占有率高、掌握关键核心技术、质量效益优的排头兵企业，对于提升中小企业自身的竞争力，以及提升产业链、供应链稳定性和竞争力具有重大意义。公司已入选工信部专精特新小巨人企业名单。",
		"国企改革": "公司属于国有企业。公司的最终控制人为国家开发投资集团有限公司。",
		"储能": "2020年9月4日公司互动：公司专注于汽车储能系统产品的研发、制造、销售和服务，主要产品为传统能源和新能源车储能系统、轻量化复合材料产品等。"
	},
	"亮点": "从事(主要是乘用车)汽车燃油系统的汽车零部件制造企业",
	"同业": "底盘系统:  拓普集团  富奥股份  兆丰股份  凯众股份  纽泰格  保隆科技  正裕工业"
}