{
	"名称": "力聚热能",
	"code": "603391",
	"亮点": "热水锅炉细分领域市占率国内第一",
	"概念": "工业互联网，专精特新，融资融券",
	"分类": "小盘股",
	"全名": "浙江力聚热能装备股份有限公司",
	"地域": "浙江省",
	"行业": "机械设备—专用设备",
	"业务": "热水锅炉与蒸汽锅炉的研发、生产和销售。",
	"产品": "真空相变热水锅炉、微压相变热水锅炉、电极真空/微压相变热水锅炉、常规燃气蒸汽锅炉、燃气蒸汽发生器、电极相变蒸汽锅炉",
	"概念详情": {
		"工业互联网": "根据公司招股说明书：公司拟使用募集资金建设“基于工业互联网平台的年产500套大功率超低氮燃气锅炉产业化项目”“年产1,500套超低氮蒸汽锅炉产业化项目”以及“年产1,000套超低氮燃气锅炉产业化项目”。",
		"专精特新": "专精特新“小巨人”企业是全国中小企业评定工作中最高等级、最具权威的荣誉称号，是指专注于细分市场、创新能力强、市场占有率高、掌握关键核心技术、质量效益优的排头兵企业，对于提升中小企业自身的竞争力，以及提升产业链、供应链稳定性和竞争力具有重大意义。公司已入选工信部国家级专精特新小巨人企业名单。"
	},
	"概念xgb": {},
	"同业": "锅炉:  海陆重工  西子洁能  华西能源  华光环能  川润股份  金财互联  迪森股份",
	"概念x": ""
}