{
	"名称": "禾丰股份",
	"code": "603609",
	"全名": "禾丰食品股份有限公司",
	"地域": "辽宁省",
	"分类": "中盘股",
	"财务": "",
	"行业": "农林牧渔—饲料",
	"业务": "饲料及饲料原料贸易的生产、销售。",
	"产品": "饲料、肉禽、原料贸易、生猪、其他",
	"概念": "养鸡，猪肉，生态农业，宠物经济，沪股通，融资融券",
	"概念y": "中证1000-100%  饲料-48%  畜牧业-35%  业绩预增-11%  猪肉-7%  生态农业-7%  养猪-4%  鸡肉-4%  家禽养殖-3%  沪股通-2%",
	"概念详情": {
		"养鸡": "2023年半年报：公司肉禽板块产能主要分布于东北三省、河北、河南、山东等地，业务划分为养殖、加工、深加工三大事业群，一条龙的产业链涵盖肉种鸡养殖、孵化、饲料生产、商品代肉鸡养殖、肉鸡屠宰加工、调理品与熟食深加工等业务环节。",
		"猪肉": "公司主营业务包括饲料及饲料原料贸易业务、肉禽业务、生猪业务。",
		"生态农业": "公司是东北地区最大的农牧集团之一，其中饲料业务收入超过营业收入的70%，是公司的主要业务。猪饲料是公司最主要和最具优势的饲料品种。2011年-2013年，公司饲料业务毛利率分别为10.51%、10.14%、10.24%，保持相对稳定。但2012-2013年公司业绩受下游养殖业景气下滑影响，连续两年下滑；2011-2013年公司归属普通股股东的净利润分别为2.70亿元、2.38亿元和1.74亿元。",
		"宠物经济": "2019年6月2日互动平台回复：公司参股的派美特旗下目前有三十家宠物医院，另外有两家宠物药品及宠物用品贸易公司。"
	},
	"亮点": "拥有饲料与生猪养殖、肉禽产业化、原料贸易等三大核心业务",
	"同业": "饲料:  大北农  唐人神  新希望  正邦科技  正虹科技  圣农发展  仙坛股份  民和股份  益生股份  温氏股份  牧原股份  邦基科技  播恩集团  通威股份  天康生物  粤海饲料  美农生物  海大集团  金新农  *ST傲农  ST天邦",
	"概念xgb": {
		"回购": "24年6月，拟1.5亿元至3亿元回购公司股份",
		"养鸡": "国内白鸡行业举足轻重的龙头企业；公司肉禽板块产能主要分布于东北三省、河北、河南、山东等地，业务划分为养殖、加工、深加工三大事业群，一条龙的产业链涵盖肉种鸡养殖、孵化、饲料生产、商品代肉鸡养殖、肉鸡屠宰加工、调理品与熟食深加工等业务环节",
		"饲料": "东北最大的饲料企业，商品饲料销量居于全国前列；公司饲料产品包括猪、禽、反刍等动物饲料，产品覆盖全国29个省级行政区，并在尼泊尔、印尼、菲律宾等国家建有饲料工厂",
		"养猪": "公司养猪业务通过自建及合作模式，涵盖种猪养殖与销售、商品仔猪销售、育肥猪放养及少量自养、生猪屠宰等环节，建立了全面生物安全、先进育种和科学养殖管理体系，产品包括种猪、商品仔猪、育肥猪及屠宰后的猪肉产品",
		"大农业": "国内白鸡行业举足轻重的龙头企业；公司肉禽板块产能主要分布于东北三省、河北、河南、山东等地，业务划分为养殖、加工、深加工三大事业群，一条龙的产业链涵盖肉种鸡养殖、孵化、饲料生产、商品代肉鸡养殖、肉鸡屠宰加工、调理品与熟食深加工等业务环节",
		"宠物经济": "公司参股的派美特公司旗下有三十余家宠物医院及两家宠物药品和用品贸易公司，且宠物医院还通过代加工方式生产销售猫粮及狗粮"
	},
	"概念x": "回购   养鸡   饲料   养猪   大农业   宠物经济"
}