{
	"名称": "永茂泰",
	"code": "605208",
	"亮点": "国内先进的铝合金生产企业之一",
	"概念": "一体化压铸，汽车热管理，新能源汽车，减速器，融资融券",
	"同业": "发动机零配件:  文灿股份  广东鸿图  泉峰汽车  怡球资源  顺博合金  天普股份  瑜欣电子  东利机械  泰祥股份  恒勃股份  锡南科技  威孚高科  渤海汽车  东睦股份  银轮股份  ST八菱  天润工业  中原内配  富临精工  秦安股份  派生科技  新坐标  贝斯特  雪龙集团  长源东谷",
	"分类": "小盘股",
	"全名": "上海永茂泰汽车科技股份有限公司",
	"地域": "上海市",
	"行业": "有色金属—工业金属",
	"业务": "汽车用铸造铝合金和铝合金零部件的研发、生产和销售。",
	"产品": "铝合金锭、铝合金液、汽车发动机下缸体、汽车发动机油底壳、汽车空调压缩机缸体缸盖、汽车涡轮增压器壳体、汽车变速箱端盖、模组支架、其他各类支架",
	"概念y": "贵金属-10%  汽车零部件-10%",
	"概念详情": {
		"一体化压铸": "铝合金汽车零部件业务为永茂泰重点发展的业务，根据客户需求和产品订单情况，公司未来也会承接中大型的压铸件产品。公司目前尚未直接供货给蔚来、小鹏和比亚迪",
		"汽车热管理": "公司拥有汽车零配件业务，重点开发新能源汽车驱动系统（电池包、电机、减速箱、电控）、车身、卡钳、汽车空调压缩机等。",
		"新能源汽车": "公司陆续开拓了博格华纳、联合电子、华域麦格纳等知名汽车零部件客户，在新能源汽车用铝合金零部件领域取得了较大进展，新能源汽车模组支架、电池包前端板等新产品逐步实现量产。",
		"减速器": "2021年8月5日公司互动：公司现有新能源汽车铝合金零部件产品包括电池包模组支架、隔断、前端板，电机端盖、减速器壳体等产品。其中大众MEB的电池包隔断、减速器壳体和电机端盖已量产。"
	}
}