{
	"名称": "龙版传媒",
	"code": "605577",
	"亮点": "黑龙江财政厅旗下，拥有出版物“编、印、发”完整的产业链，《格言》成为全国最受青少年喜爱的语言类期刊之一",
	"概念": "文化传媒概念，IP经济(谷子经济)，黑龙江自贸区，国企改革，沪股通，一带一路，在线教育，振兴东北",
	"同业": "图书出版:  中国出版  中国科传  南方传媒  新华文轩  凤凰传媒  中南传媒  果麦文化  荣信文化  新经典  读客文化  浙版传媒  内蒙新华  中文传媒  山东出版  皖新传媒  中信出版  长江传媒",
	"分类": "小盘股",
	"全名": "黑龙江出版传媒股份有限公司",
	"地域": "黑龙江省",
	"行业": "传媒—出版",
	"业务": "图书、期刊及电子出版物的出版、发行及印刷服务等业务。",
	"产品": "教材教辅、一般图书、物资贸易",
	"概念y": "",
	"概念详情": {
		"文化传媒概念": "公司主营出版物(图书、电子音像制品、期刊与报纸等)“编、印、发”完整的产业链,具备出版物的编辑和出版、印刷、批发及零售、物资贸易等传统业务,同时融合数字出版等新兴业态于一体。",
		"IP经济(谷子经济)": "2023年度股东大会会议材料：核心竞争力不断提升。打造融合出版新产品、新服务、新模式，《白山黑水铸丰碑聆听红色故事》电子出版物、《印象中东铁路》元宇宙展馆等融合出版项目落地结果，“胖不墩儿”IP形象文创、“京剧猫”戏剧故事等产品实现“一次开发多种产品，一种产品多个形态”。",
		"黑龙江自贸区": "公司地址是黑龙江省哈尔滨市松北区龙川路258号",
		"在线教育": "公司将大力发挥教育出版资源优势，不断充实在线教育领域实力，努力将在线教育打造成公司未来发展新的经济增长点。",
		"国企改革": "公司属于国有企业。公司的最终控制人为黑龙江省财政厅。",
		"一带一路": "2022年3月15日互动易回复：公司作为边疆文化企业公司充分发挥区位优势，紧紧抓住“一带一路”契机，在俄罗斯设立中俄语言文化交流中心，有计划地开展文化交流活动，进行版权信息互通，积极促进版权贸易。"
	},
	"概念x": "直播/短视频   振兴东北   传媒   中俄贸易   国企改革   在线教育",
	"概念xgb": {
		"直播/短视频": "公司正在探索用短视频、直播带货等方式拓展线上销售业务",
		"振兴东北": "公司控股股东为黑龙江出版集团有限公司；公司主要从事图书、期刊及电子出版物的出版、发行及印刷服务等业务",
		"传媒": "东北地区出版发行行业的领先企业之一；公司主要从事图书、期刊及电子出版物的出版、发行及印刷服务等业务，致力于为消费者提供知识、信息，并向中小学生提供教材、教辅等学习资料，以满足受众的文化消费需求和教育需求",
		"中俄贸易": "作为边疆文化企业，公司充分发挥区位优势，紧紧抓住“一带一路”契机，在俄罗斯设立中俄语言文化交流中心，有计划地开展文化交流活动，进行版权信息互通，积极促进版权贸易",
		"国企改革": "实控人黑龙江出版集团；公司主要从事图书、期刊及电子出版物的出版、发行及印刷服务等业务",
		"在线教育": "公司凭借自身教材教辅内容研发优势，综合运用数字出版技术，逐步开发、完善教材及其延伸产品等数字资源服务，满足中小学生在线教育服务需求"
	}
}