{
	"名称": "福光股份",
	"code": "688010",
	"概念": "专精特新，超清视频，华为概念，安防，军工，军民融合，区块链，融资融券",
	"财务": "",
	"分类": "小盘股",
	"全名": "福建福光股份有限公司",
	"地域": "福建省",
	"行业": "电子—光学光电子",
	"业务": "特种及民用光学镜头、光电系统、光学元组件等产品科研生产。",
	"产品": "特种光学镜头及光电系统、安防镜头、车载镜头、红外镜头、机器视觉镜头",
	"概念详情": {
		"华为概念": "物联网镜头、AI镜头是公司当前重点布局的新兴领域，公司已经与华为、旷视科技、依图科技、云从科技、地平线、海康威视等人工智能知名企业建立了合作关系。",
		"超清视频": "2017年公司在安防镜头全球市场占有率达到11.8%（数据来源TSR），引领安防监控领域超高清视频技术的创新应用并率先设计开发出8K高清连续变焦镜头。",
		"军工": "公司产品包括激光、紫外、可见光、红外系列全光谱镜头及光电系统，其定制产品系列主要包含军用特种光学镜头及光电系统，广泛应用于“神舟系列”、“嫦娥探月”、“火星探测”等国家重大航天任务及尖端武器装备，核心客户涵盖中国科学院及各大军工集团下属科研院所、企业。",
		"军民融合": "公司军用产品注重定制化经营模式，民用产品适应市场需求实现大批量生产，并实践军民融合机制，加速军品、民品的技术创新和先进技术的产业化。公司践行军民融合机制的建立，通过军用技术转民用以及民用技术转军用等各项措施，极大提升了军品和民品的高效创新。",
		"安防": "公司产品包含民用安防镜头，并广泛应用于平安城市、智慧城市、物联网、车联网、智能制造等领域，是安讯士、大华股份等安防龙头企业的主要镜头供应商，其安防镜头全球市场占有率2017年达到11.8%。",
		"区块链": "福建省算域大数据科技有限公司主营业务为：专业从事人工智能应用服务、区块链信息平台运营服务。"
	},
	"概念y": "工业4.0-10%  快递物流-10%  机器视觉-10%  航天-10%  军工-0%  数字货币-0%",
	"亮点": "产品包括全光谱镜头及光电系统，广泛应用于航天任务及尖端武器装备",
	"同业": "光学镜头:  联合光电  宇瞳光学  乐凯胶片  永新光学  蓝特光学  腾景科技  凤凰光学  中光学  力鼎光电  美迪凯"
}