{
	"名称": "佳华科技",
	"code": "688051",
	"概念": "大数据，智慧城市，华为概念，区块链，人工智能，融资融券，数据中心，物联网，云计算",
	"财务": "",
	"分类": "小盘股",
	"全名": "罗克佳华科技集团股份有限公司",
	"地域": "北京市",
	"行业": "计算机—IT服务Ⅱ",
	"业务": "为智慧环保和智慧城市领域的应用场景，提供基于物联网综合技术的软硬件产品、解决方案及数据服务。",
	"产品": "云链共享平台、海东青物联网平台、数据安全管理系统、AI云平台、区块链可信存证",
	"概念详情": {
		"科创次新股": "公司上市日期为2020-03-20，主营为物联网智能制造、数据采集、数据融合、智能分析",
		"云计算": "云链数据库指公司自主研发，能够融合、承载海量多源数据的一种数据库技术。该技术结合“云计算”+“区块链”，实现不同信息系统数据的实时同步交换及数据融合。",
		"数据中心": "2020年4月20日公司在互动平台称：在自用方面，公司通过云链平台为政府、企业客户等服务对象提供物联网云服务，形成较强的竞争力，使公司在获取订单时有较强的成本优势和技术优势。在向第三方提供服务方面，我们可以为优质客户提供IDC服务及PAAS服务，并和这些优质客户在新业务领域方面拓展更多的业务合作机会。两方面结合，共同推进物联网云服务基地发挥更大的价值，与公司主营业务相互赋能，提高公司核心竞争力和持续增长。物联网云服务中心已经有金融机构进驻，并完成数据中心机房登记评定工作，取得国家数据中心A级证书。",
		"新股与次新股": "公司上市日期为2020-03-20，主营为物联网智能制造、数据采集、数据融合、智能分析",
		"物联网": "公司致力于在物联网各个垂直应用领域进行业务拓展,通过物联网感知层、网络层、应用层的搭建,感知数据,并搭建应用平台,帮助客户运用物联网、提升物联网数据运用水平。",
		"区块链": "公司自主研发了云链数据库。公司应用云链数据库中的“云计算”功能，处理日益庞大的数据集，对各种数据进行有机整合，解决了数据不统一、不规范、不完整的问题，为环境管理和生态治理提供数据服务及信息支撑。应用云链数据库中的“区块链”功能，公司建立不同信息系统背后数据库的实时同步交换平台，实现不同系统之间数据的交换与融合。",
		"人工智能": "目前公司人工智能AI技术支持20余种智慧城市场景下的复杂AI算法，能够快速智能识别。",
		"大数据": "发行人开发的“云链数据库”技术,能快速建立各类系统之间的数据交换,建立起一个大数据交换平台。",
		"智慧城市": "招股说明书披露：在智慧城市领域，公司以智慧环保为切入点和导流点，同时结合公司在建筑智能化领域的基础，横向拓展智慧城市其他具体应用领域。",
		"华为概念": "2020年3月27日公司在互动平台称：公司是华为鲲鹏的合作伙伴情况。"
	},
	"概念y": "智慧城市-10%  云计算数据中心-10%  大气治理-10%  环保-10%  物联网-0%",
	"亮点": "拥有国际软件能力成熟度认证评估最高资质CMMIL5资质",
	"同业": "物联网:  南威软件  数字政通  太极股份  易华录  银江股份  映翰通  力合微  宜通世纪  日海智能  美格智能  移为通信  移远通信  广和通"
}