{
	"名称": "英科再生",
	"code": "688087",
	"亮点": "国内领先的PS塑料再生循环利用企业",
	"概念": "固废处理，节能环保，碳中和，沪股通，融资融券",
	"同业": "资源回收:  格林美  怡球资源  中再资环  浩通科技  华新环保  赤峰黄金",
	"分类": "小盘股",
	"全名": "山东英科环保再生资源股份有限公司",
	"地域": "山东省",
	"行业": "基础化工—塑料",
	"业务": "可再生塑料的回收、再生、利用。",
	"产品": "A系列泡沫冷压机、Z系列泡沫压缩机、M系列泡沫热熔机、P系列减容除水机、再生PS粒子、再生PET材料、再生PS线条、环保成品框、再生PET片材",
	"概念y": "环保-10%  固废处理-10%",
	"概念详情": {
		"固废处理": "公司是一家塑料循环再生利用的高科技制造商,从事可再生塑料的回收、再生、利用业务,公司创新的打通了塑料循环再利用的全产业链,是将塑料回收再生与时尚消费品运用完美嫁接的独创企业。",
		"节能环保": "公司已具备一定规模的PS塑料回收再生业务并正在建设PET和PP、PE等塑料品类的回收再生项目。",
		"碳中和": "根据公司官网：公司具备每年回收再利用约15万吨塑料的能力，帮助全球每年减少30万吨碳排放、节省45万吨原油资源、减少约200万棵树木被砍伐，成立至今已累积减少约250万吨碳排放，节省约375万吨原油资源，减少约2500万棵树木被砍伐。"
	}
}