{
	"名称": "斯瑞新材",
	"code": "688102",
	"亮点": "高强高导铜合金材料及制品制造商，铜铬触头市场占有率处于国内领先地位",
	"概念": "芯片概念，共封装光学（CPO），3D打印，充电桩，航空发动机，沪股通，融资融券，新材料概念，新能源汽车，医疗器械概念",
	"同业": "合金材料:  博威合金  东阳光  钢研高纳  立中集团  合金投资  宜安科技  深圳新星  福达合金  银邦股份  丰华股份  光智科技  鄂尔多斯  图南股份  欧科亿  中洲特材  新锐股份  广大特材  宝武镁业",
	"分类": "小盘股",
	"全名": "陕西斯瑞新材料股份有限公司",
	"地域": "陕西省",
	"行业": "有色金属—金属新材料",
	"业务": "提供高强高导铜合金材料及制品,中高压电接触材料及制品,高性能金属铬粉,CT和DR球管零组件等产品的关键基础材料和零组件制造商。",
	"产品": "高强高导铜合金材料及制品、中高压电接触材料及制品、高性能金属铬粉、CT和DR球管零组件、新一代铜铁合金材料、光模块芯片基座、液体火箭发动机推力室内壁",
	"概念详情": {
		"芯片概念": "2023年5月31日公司调研显示：公司研发的半导体冷却板主要应用在芯片半导体薄膜沉积设备（PVD和CVD）。其中PVD设备用冷却板产品陆续通过客户验证，已进入小批量供货阶段。CVD设备用冷却板正在开发中。",
		"共封装光学（CPO）": "2023年6月5日互动易回复：光模块芯片基座是光模块的重要零组件，2022年公司成功进入光模块领域，并通过多家客户的应用验证，已开始实现批量稳定的供货。2023年公司继续扩大产能，支持光通信行业向400G、800G、1.6T快速发展。",
		"3D打印": "2023年7月18日互动易回复：公司自主开发了CuCr电触头3D打印技术，能够生产多品种、复杂结构的产品。后续公司会继续进行电子束、激光等3D打印技术的研发；2）公司具备年产60吨各类高性能铜合金粉末的制造能力，该合金粉末可以应用于航天3D打印关键零件等领域；公司生产的高性能金属铬粉，可应用于增材制造行业3D打印、注射成型、激光熔覆等领域。",
		"新材料概念": "公司以坚守创新驱动发展，持续不断研发、制造各类合金新材料、服务国家经济社会发展需要，在部分领域解决国家“卡脖子”问题，填补国家新材料领域空白为使命，以成为全球细分领域新材料的领跑者为愿景。",
		"医疗器械概念": "陕西斯瑞新材料股份有限公司是一家以轨道交通、电力电子、航空航天、医疗影像等高端应用领域为目标市场，公司是CT和DR球管零组件等产品的关键基础材料和零组件制造商。",
		"充电桩": "2022年11月14日投资者关系记录表：公司的高强高导铜合金材料可用于新能源汽车高电压大电流连接器、快速充电用高性能接插件和直流接触器。",
		"新能源汽车": "2022年11月14日投资者关系纪录表：公司的主要产品为中高压电真空接触材料及制品、高强高导铜合金材料及制品、高性能金属铬粉、医疗影像零组件等，下游的行业赛道有新能源汽车。",
		"航空发动机": "2023年4月10日互动易回复：公司高强高导铜合金材料应用于航空航天的液体火箭发动机燃烧室内衬。液体火箭发动机燃烧室内衬是发动机重要核心部件。"
	}
}