{
	"名称": "友车科技",
	"code": "688479",
	"亮点": "国内汽车营销与后市场服务领域软件产品及云服务提供商龙头",
	"概念": "数字经济，融资融券",
	"分类": "小盘股",
	"全名": "用友汽车信息科技(上海)股份有限公司",
	"地域": "上海市",
	"行业": "计算机—软件开发",
	"业务": "向汽车、工程机械、摩托车等行业客户提供营销与后市场服务领域的数智化解决方案、软件及云服务。",
	"产品": "车企营销系统、车主服务平台、汽车产业生态服务平台、系统运维服务、智能设备销售",
	"概念详情": {
		"数字经济": "根据公司上市公告书：公司主要面向汽车行业的整车厂、经销商、服务站等客户，提供营销与后市场服务领域的数智化解决方案、云服务、软件及专业服务，并打造汽车产业链上下游和跨行业融合的数字化生态体系平台，赋能汽车行业数字化转型。"
	},
	"同业": "细分行业软件:  多伦科技  三维天地  工大科雅  世纪恒通",
	"概念x": "国产软件   汽车销售",
	"概念xgb": {
		"国产软件": "国内领先的汽车行业营销领域软件与云服务提供商；公司主要面向汽车、工程机械、摩托车等行业客户，提供营销与后市场服务领域的数智化解决方案、软件及云服务，主要产品包括车企营销系统、车主服务平台、汽车产业生态服务平台、系统运维服务等，已为超百家整车厂、1.5万家经销商提供服务",
		"汽车销售": "公司主要面向汽车行业的整车厂、经销商、服务站等客户，提供营销与后市场服务领域的数智化解决方案、云服务、软件及专业服务，并打造汽车产业链上下游和跨行业融合的数字化生态体系平台，赋能汽车行业数字化转型\n"
	}
}