{
	"名称": "富信科技",
	"code": "688662",
	"亮点": "国内外少数全产业链半导体热电技术解决方案提供商之一",
	"概念": "芯片概念，储能，5G，覆铜板概念，共封装光学(CPO)，融资融券",
	"同业": "家电零部件:  热威股份  康盛股份  万朗磁塑  宏昌科技  朗迪集团  华翔股份  德业股份  三花智控  奇精机械  东方电热  金海高科  香农芯创",
	"分类": "小盘股",
	"全名": "广东富信科技股份有限公司",
	"地域": "广东省",
	"行业": "电子—其他电子Ⅱ",
	"业务": "半导体热电器件及以其为核心的热电系统、热电整机应用产品的研发、设计、制造与销售。",
	"产品": "单级热电制冷器件、型热电制冷器件、级热电制冷器件、差发电器件",
	"概念y": "",
	"概念详情": {
		"芯片概念": "广东富信科技股份有限公司是国内外少数全产业链半导体热电技术解决方案提供商之一，主营业务为半导体热电器件及以其为核心的热电系统、热电整机应用产品的研发、设计、制造与销售业务。",
		"储能": "根据2024年11月1日投资者关系记录表，公司的储能液冷除湿系统可用于储能电池柜，半导体热电制冷技术制成的除湿机具有体积小、湿度控制精度高等优势，可以在储能柜中灵活放置并对指定空间进行针对性除湿，有效解决了因储能柜中的电池密度大、空间狭小导致风道狭窄空气流动差的问题，保证储能设备的运行安全。随着液冷技术在电化学储能热管理渗透率的快速提高，半导体制冷除湿机有望形成公司新的利润增长点。",
		"5G": "公司生产的用于5G网络中光模块温控的高性能微型热电制冷器件已于2020年向客户小批量供货。",
		"共封装光学(CPO)": "根据2024年半年报，报告期内，公司已与多家光模块厂商积极开展应用于数通400G/800G高速率光模块的MicroTEC的项目开发，并实现产品送样。"
	},
	"概念x": "5G   光通信   激光雷达",
	"概念xgb": {
		"5G": "公司研制的应用于5G网络中光模块温控的高性能微型热电制冷器件，其可靠性已达到光电子器件通用可靠性保证要求（GR-468-CORE）和美国国防部发布的微电子器件试验方法标准（MIL-STD-883）两项国际先进测试标准的要求",
		"光通信": "公司的温控技术为半导体制冷技术，能够实现局部、精准控温，是国内少数能够批量生产光通信应用高性能超微型热电制冷器件的企业；公司于2022年实现了用于5G网络中光模块温控的高性能微型热电制冷器件批量生产",
		"激光雷达": "公司已通过IATF16949汽车行业质量管理体系认证，并积极开展车载激光雷达应用TEC控温方案的研发，目前尚未进入车企激光雷达供应链"
	}
}