{
	"名称": "天铭科技",
	"code": "836270",
	"亮点": "越野改装装备及其他相关辅件制造商",
	"概念": "高股息精选，军工，人民币贬值受益，融资融券，专精特新",
	"分类": "小盘股",
	"全名": "杭州天铭科技股份有限公司",
	"地域": "浙江省",
	"行业": "汽车—汽车零部件",
	"业务": "绞盘、电动踏板、车载空压机、尾门合页和其他辅件等汽车越野改装件的设计、研发、生产和销售。",
	"产品": "绞盘、电动踏板、车载空压机、尾门合页、其他越野改装件及附件",
	"概念详情": {
		"专精特新": "专精特新“小巨人”企业是全国中小企业评定工作中最高等级、最具权威的荣誉称号，是指专注于细分市场、创新能力强、市场占有率高、掌握关键核心技术、质量效益优的排头兵企业，对于提升中小企业自身的竞争力，以及提升产业链、供应链稳定性和竞争力具有重大意义。公司已入选工信部国家级专精特新小巨人企业名单。",
		"人民币贬值受益": "根据2024年半年报，公司海外营收占比为66.69%，受益于人民币贬值。",
		"军工": "2023年半年报：公司主要从事绞盘、电动踏板、车载空压机、尾门合页和其他辅件等汽车越野改装件的设计、研发、生产和销售，产品主要应用于山地越野车、皮卡、军车、SUV等车型。",
		"高股息精选": "天铭科技连续3年股息率分别为：6.97%，3.84%，3.11%"
	},
	"同业": ":  ",
	"概念x": "",
	"概念xgb": {}
}