{
	"名称": "视声智能",
	"code": "870976",
	"亮点": "主营智能家居、可视对讲、液晶显示屏及模组",
	"概念": "安防，高股息精选，跨境电商，人脸识别，融资融券，数据安全，网络安全，智能家居",
	"分类": "小盘股",
	"全名": "广州视声智能股份有限公司",
	"地域": "广东省",
	"行业": "计算机—计算机设备",
	"业务": "智能家居、可视对讲等智能化设备和液晶显示屏及模组的研发设计、生产制造和销售以及配套技术服务。",
	"产品": "智能家居、可视对讲、液晶显示屏及模组",
	"概念详情": {
		"智能家居": "根据公司招股说明书：公司主营业务是智能家居、可视对讲等智能化设备和液晶显示屏及模组的研发设计、生产制造和销售以及配套技术服务。主要产品和服务为智能家居、可视对讲、液晶显示屏及模组。",
		"网络安全": "2023年年报：报告期内,公司秉持“让生活更智能，让智能更简单”的愿景，以发展新质生产力为内核，坚持KNX技术领域的不断突破，率先在国内推出KNX网络安全产品，成为全球领先的KNX网络全产品制造商，有力推动了公司高质量发展之路。",
		"数据安全": "2023年半年度报告：公司成功通过KNX安全协议栈认证，该技术符合高等级的加密标准AES128CCM，并通过VDE安全认证，可提供IP安全和数据安全双重保护，在安全技术实力上位居行业前列。",
		"人脸识别": "据公司官网，公司产品具备双目宽动态+近红外摄像头，夜间高亮LED灯自动补光。支持多张人脸检测、人脸跟踪、活体检测、口罩识别等功能。",
		"跨境电商": "根据公司招股说明书：公司的直销模式主要以线下为主，同时借助Amazon、eBay、阿里巴巴、速卖通等电商平台，辅以少量线上销售。",
		"安防": "2024年5月17日互动易：公司自设立以来一直专注并深耕于智慧建筑和智能安防领域，通过持续的自主创新与市场开拓，已形成先进的核心技术、完善的产品体系，在行业内树立了良好的品牌形象，综合竞争优势明显。",
		"高股息精选": "视声智能连续3年股息率分别为：8.57%，9.38%，3.23%"
	},
	"同业": ":  ",
	"概念x": "",
	"概念xgb": {}
}