{
	"名称": "新威凌",
	"code": "871634",
	"亮点": "主营球状锌粉，产能规模国内居前",
	"概念": "储能，金属锌，融资融券，专精特新",
	"分类": "小盘股",
	"全名": "湖南新威凌金属新材料科技股份有限公司",
	"地域": "湖南省",
	"行业": "有色金属—工业金属",
	"业务": "常规锌粉及超细高纯锌粉的研发、生产和销售。",
	"产品": "球状锌粉、片状锌粉、雾化法锌粉",
	"概念详情": {
		"金属锌": "湖南新威凌金属新材料科技股份有限公司的主营业务为常规锌粉及超细高纯锌粉的研发、生产和销售。公司的主要产品有富锌防腐涂料专用锌粉、粉镀渗锌专用锌粉、化学工业用锌粉、冶金工业专用锌粉、医药农药专用锌粉。",
		"专精特新": "专精特新“小巨人”企业是全国中小企业评定工作中最高等级、最具权威的荣誉称号，是指专注于细分市场、创新能力强、市场占有率高、掌握关键核心技术、质量效益优的排头兵企业，对于提升中小企业自身的竞争力，以及提升产业链、供应链稳定性和竞争力具有重大意义。公司已入选工信部国家级专精特新小巨人企业名单。",
		"储能": "根据2024年10月10日投资者活动记录表，公司产品片状锌粉主要应用领域为汽车配件、储能（含储能电池、光伏构件、风电构件）配套设备设施、军工配件、锌铝涂层、达克罗涂层等。"
	},
	"同业": ":  ",
	"概念x": "",
	"概念xgb": {}
}